Workbook

Sheet 어휘 - 표 1 스냅샷
A1: No | B1: 영어단어 | C1: 어원 | D1: 구분 | E1: 발음 | F1: 힌트 | G1: 뜻 | H1: 문장 | I1: 영어문장 | J1: 외운것 | K1: 틀린것 | L1: 날짜
A2: 1 | B2: ball | C2: ball | D2: ball | E2: [bɔːl] | F2: 부풀어 오르다(b) 모든(all) 면이 그렇게 생긴 것은 ‘공’ | G2: 공 | H2: The children played with a colorful ball in the park. | I2: {=SUBSTITUTE(H2,B2,"( )")} -> The children played with a colorful ( ) in the park. | J2: {=SUMIF('외운 것 - 엑셀다운로드 파일(붙여넣기)'!A3:A562,A2,'외운 것 - 엑셀다운로드 파일(붙여넣기)'!D3:D562)} -> 3 | K2: {=_xlfn.COUNTIFS('외운 것 - 엑셀다운로드 파일(붙여넣기)'!A3:A562,A2,'외운 것 - 엑셀다운로드 파일(붙여넣기)'!D3:D562,0)} -> 0 | L2: {=IF(J2>=3,_xlfn.XLOOKUP(A2,'외운 것 - 엑셀다운로드 파일(붙여넣기)'!A3:A562,'외운 것 - 엑셀다운로드 파일(붙여넣기)'!C3:C562,0,-1),0)} -> 2026-03-14
A3: 2 | B3: balloon | C3: ball | D3: ball | E3: [bəlúːn] | F3: 부풀어 오른 공(ball)이 나중에 아래(oo-u)로 바람이 빠져 나오면 없어지는(n) 것 ‘풍선, 기구’ | G3: 풍선, 기구 | H3: She bought a red balloon for her birthday party. | I3: {=SUBSTITUTE(H3,B3,"( )")} -> She bought a red ( ) for her birthday party. | J3: {=SUMIF('외운 것 - 엑셀다운로드 파일(붙여넣기)'!A3:A562,A3,'외운 것 - 엑셀다운로드 파일(붙여넣기)'!D3:D562)} -> 3 | K3: {=_xlfn.COUNTIFS('외운 것 - 엑셀다운로드 파일(붙여넣기)'!A3:A562,A3,'외운 것 - 엑셀다운로드 파일(붙여넣기)'!D3:D562,0)} -> 1 | L3: {=IF(J3>=3,_xlfn.XLOOKUP(A3,'외운 것 - 엑셀다운로드 파일(붙여넣기)'!A3:A562,'외운 것 - 엑셀다운로드 파일(붙여넣기)'!C3:C562,0,-1),0)} -> 2026-03-16
A4: 3 | B4: bell | C4: bell | D4: bell | E4: [bel] | F4: 공처럼 불룩한(b) 모양의 ‘종, 벨’ | G4: 종, 벨 | H4: The school bell rang to signal the end of class. | I4: {=SUBSTITUTE(H4,B4,"( )")} -> The school ( ) rang to signal the end of class. | J4: {=SUMIF('외운 것 - 엑셀다운로드 파일(붙여넣기)'!A3:A562,A4,'외운 것 - 엑셀다운로드 파일(붙여넣기)'!D3:D562)} -> 3 | K4: {=_xlfn.COUNTIFS('외운 것 - 엑셀다운로드 파일(붙여넣기)'!A3:A562,A4,'외운 것 - 엑셀다운로드 파일(붙여넣기)'!D3:D562,0)} -> 0 | L4: {=IF(J4>=3,_xlfn.XLOOKUP(A4,'외운 것 - 엑셀다운로드 파일(붙여넣기)'!A3:A562,'외운 것 - 엑셀다운로드 파일(붙여넣기)'!C3:C562,0,-1),0)} -> 2026-03-14
A5: 4 | B5: belly | C5: bell | D5: bell | E5: [béli] | F5: 불룩한 bell에 확장을 의미하는 y가 더해저서 더욱더 불룩한 모습이 되는 ‘불룩한 배’ | G5: 불룩한 배 | H5: The cat's belly was soft and warm. | I5: {=SUBSTITUTE(H5,B5,"( )")} -> The cat's ( ) was soft and warm. | J5: {=SUMIF('외운 것 - 엑셀다운로드 파일(붙여넣기)'!A3:A562,A5,'외운 것 - 엑셀다운로드 파일(붙여넣기)'!D3:D562)} -> 3 | K5: {=_xlfn.COUNTIFS('외운 것 - 엑셀다운로드 파일(붙여넣기)'!A3:A562,A5,'외운 것 - 엑셀다운로드 파일(붙여넣기)'!D3:D562,0)} -> 0 | L5: {=IF(J5>=3,_xlfn.XLOOKUP(A5,'외운 것 - 엑셀다운로드 파일(붙여넣기)'!A3:A562,'외운 것 - 엑셀다운로드 파일(붙여넣기)'!C3:C562,0,-1),0)} -> 2026-03-14
A6: 5 | B6: bullet | C6: ball | D6: ball | E6: [búlit] | F6: 처음에 공(ball)처럼 생긴 작은 덩어리(let)였던 ‘총알’ | G6: 총알 | H6: The detective found a bullet at the crime scene. | I6: {=SUBSTITUTE(H6,B6,"( )")} -> The detective found a ( ) at the crime scene. | J6: {=SUMIF('외운 것 - 엑셀다운로드 파일(붙여넣기)'!A3:A562,A6,'외운 것 - 엑셀다운로드 파일(붙여넣기)'!D3:D562)} -> 3 | K6: {=_xlfn.COUNTIFS('외운 것 - 엑셀다운로드 파일(붙여넣기)'!A3:A562,A6,'외운 것 - 엑셀다운로드 파일(붙여넣기)'!D3:D562,0)} -> 0 | L6: {=IF(J6>=3,_xlfn.XLOOKUP(A6,'외운 것 - 엑셀다운로드 파일(붙여넣기)'!A3:A562,'외운 것 - 엑셀다운로드 파일(붙여넣기)'!C3:C562,0,-1),0)} -> 2026-03-14
A7: 6 | B7: bulb | C7: ball | D7: ball | E7: [bʌlb] | F7: 공(ball)처럼 부풀어 오르는(b) ‘둥근 뿌리, 전구’ | G7: 둥근 뿌리, 전구 | H7: I need to replace the light bulb in the kitchen. | I7: {=SUBSTITUTE(H7,B7,"( )")} -> I need to replace the light ( ) in the kitchen. | J7: {=SUMIF('외운 것 - 엑셀다운로드 파일(붙여넣기)'!A3:A562,A7,'외운 것 - 엑셀다운로드 파일(붙여넣기)'!D3:D562)} -> 3 | K7: {=_xlfn.COUNTIFS('외운 것 - 엑셀다운로드 파일(붙여넣기)'!A3:A562,A7,'외운 것 - 엑셀다운로드 파일(붙여넣기)'!D3:D562,0)} -> 0 | L7: {=IF(J7>=3,_xlfn.XLOOKUP(A7,'외운 것 - 엑셀다운로드 파일(붙여넣기)'!A3:A562,'외운 것 - 엑셀다운로드 파일(붙여넣기)'!C3:C562,0,-1),0)} -> 2026-03-14
A8: 7 | B8: bulk | C8: ball | D8: ball | E8: [bʌlk] | F8: 공(ball)처럼 몸이 부풀어오르고 확장(k)되니 ‘큰 규모, 육중한 것’ | G8: 큰 규모, 육중한 것 | H8: He bought rice in bulk to save money. | I8: {=SUBSTITUTE(H8,B8,"( )")} -> He bought rice in ( ) to save money. | J8: {=SUMIF('외운 것 - 엑셀다운로드 파일(붙여넣기)'!A3:A562,A8,'외운 것 - 엑셀다운로드 파일(붙여넣기)'!D3:D562)} -> 3 | K8: {=_xlfn.COUNTIFS('외운 것 - 엑셀다운로드 파일(붙여넣기)'!A3:A562,A8,'외운 것 - 엑셀다운로드 파일(붙여넣기)'!D3:D562,0)} -> 0 | L8: {=IF(J8>=3,_xlfn.XLOOKUP(A8,'외운 것 - 엑셀다운로드 파일(붙여넣기)'!A3:A562,'외운 것 - 엑셀다운로드 파일(붙여넣기)'!C3:C562,0,-1),0)} -> 2026-03-14
A9: 8 | B9: base | C9: base | D9: base | E9: [beis] | F9: 불룩(b)한데 잘 보이지 않는(s) 곳에 있는 ‘바닥, 기초, 기지’ | G9: 바닥, 기초, 기지 | H9: The military base is located near the mountain. | I9: {=SUBSTITUTE(H9,B9,"( )")} -> The military ( ) is located near the mountain. | J9: {=SUMIF('외운 것 - 엑셀다운로드 파일(붙여넣기)'!A3:A562,A9,'외운 것 - 엑셀다운로드 파일(붙여넣기)'!D3:D562)} -> 3 | K9: {=_xlfn.COUNTIFS('외운 것 - 엑셀다운로드 파일(붙여넣기)'!A3:A562,A9,'외운 것 - 엑셀다운로드 파일(붙여넣기)'!D3:D562,0)} -> 0 | L9: {=IF(J9>=3,_xlfn.XLOOKUP(A9,'외운 것 - 엑셀다운로드 파일(붙여넣기)'!A3:A562,'외운 것 - 엑셀다운로드 파일(붙여넣기)'!C3:C562,0,-1),0)} -> 2026-03-14
A10: 9 | B10: basic | C10: base | D10: base | E10: [béisik] | F10: 기초, 바닥(base)의 상태(~ic)이므로 ‘기초적인, 근본적인’ | G10: 기초적인, 근본적인 | H10: You need to learn the basic principles of mathematics. | I10: {=SUBSTITUTE(H10,B10,"( )")} -> You need to learn the ( ) principles of mathematics. | J10: {=SUMIF('외운 것 - 엑셀다운로드 파일(붙여넣기)'!A3:A562,A10,'외운 것 - 엑셀다운로드 파일(붙여넣기)'!D3:D562)} -> 3 | K10: {=_xlfn.COUNTIFS('외운 것 - 엑셀다운로드 파일(붙여넣기)'!A3:A562,A10,'외운 것 - 엑셀다운로드 파일(붙여넣기)'!D3:D562,0)} -> 0 | L10: {=IF(J10>=3,_xlfn.XLOOKUP(A10,'외운 것 - 엑셀다운로드 파일(붙여넣기)'!A3:A562,'외운 것 - 엑셀다운로드 파일(붙여넣기)'!C3:C562,0,-1),0)} -> 2026-03-14
A11: 10 | B11: basement | C11: base | D11: base | E11: [béismənt] | F11: 건물의 기초(base)에 해당하는 ‘지하층, 지하실’ | G11: 지하층, 지하실 | H11: We store old furniture in our basement. | I11: {=SUBSTITUTE(H11,B11,"( )")} -> We store old furniture in our ( ). | J11: {=SUMIF('외운 것 - 엑셀다운로드 파일(붙여넣기)'!A3:A562,A11,'외운 것 - 엑셀다운로드 파일(붙여넣기)'!D3:D562)} -> 3 | K11: {=_xlfn.COUNTIFS('외운 것 - 엑셀다운로드 파일(붙여넣기)'!A3:A562,A11,'외운 것 - 엑셀다운로드 파일(붙여넣기)'!D3:D562,0)} -> 0 | L11: {=IF(J11>=3,_xlfn.XLOOKUP(A11,'외운 것 - 엑셀다운로드 파일(붙여넣기)'!A3:A562,'외운 것 - 엑셀다운로드 파일(붙여넣기)'!C3:C562,0,-1),0)} -> 2026-03-14
A12: 11 | B12: baseball | C12: base | D12: base | E12: [béisbɔ̀ːl] | F12: 1루, 2루, 3루에 둔 base(바닥)을 밟으며 ball(공)로 하는 경기, ‘야구’ | G12: 야구 | H12: My brother plays baseball every weekend. | I12: {=SUBSTITUTE(H12,B12,"( )")} -> My brother plays ( ) every weekend. | J12: {=SUMIF('외운 것 - 엑셀다운로드 파일(붙여넣기)'!A3:A562,A12,'외운 것 - 엑셀다운로드 파일(붙여넣기)'!D3:D562)} -> 3 | K12: {=_xlfn.COUNTIFS('외운 것 - 엑셀다운로드 파일(붙여넣기)'!A3:A562,A12,'외운 것 - 엑셀다운로드 파일(붙여넣기)'!D3:D562,0)} -> 0 | L12: {=IF(J12>=3,_xlfn.XLOOKUP(A12,'외운 것 - 엑셀다운로드 파일(붙여넣기)'!A3:A562,'외운 것 - 엑셀다운로드 파일(붙여넣기)'!C3:C562,0,-1),0)} -> 2026-03-14
A13: 12 | B13: bass | C13: base | D13: base | E13: [beis] | F13: 음악의 여러 파트 중에서 낮은(bass 바닥)음을 차지하는 ‘베이스, 저음’ | G13: 베이스, 저음 | H13: The bass guitar creates deep, low sounds in the band. | I13: {=SUBSTITUTE(H13,B13,"( )")} -> The ( ) guitar creates deep, low sounds in the band. | J13: {=SUMIF('외운 것 - 엑셀다운로드 파일(붙여넣기)'!A3:A562,A13,'외운 것 - 엑셀다운로드 파일(붙여넣기)'!D3:D562)} -> 3 | K13: {=_xlfn.COUNTIFS('외운 것 - 엑셀다운로드 파일(붙여넣기)'!A3:A562,A13,'외운 것 - 엑셀다운로드 파일(붙여넣기)'!D3:D562,0)} -> 0 | L13: {=IF(J13>=3,_xlfn.XLOOKUP(A13,'외운 것 - 엑셀다운로드 파일(붙여넣기)'!A3:A562,'외운 것 - 엑셀다운로드 파일(붙여넣기)'!C3:C562,0,-1),0)} -> 2026-03-14
A14: 13 | B14: blouse | C14: bl | D14: bl | E14: [blaus, blauz] | F14: (허리띠 윗 부분에서) 불룩해지고(b) 늘어진(l) 스타일의 옷, ‘블라우스’ | G14: 블라우스 | H14: She wore a silk blouse to the interview. | I14: {=SUBSTITUTE(H14,B14,"( )")} -> She wore a silk ( ) to the interview. | J14: {=SUMIF('외운 것 - 엑셀다운로드 파일(붙여넣기)'!A3:A562,A14,'외운 것 - 엑셀다운로드 파일(붙여넣기)'!D3:D562)} -> 3 | K14: {=_xlfn.COUNTIFS('외운 것 - 엑셀다운로드 파일(붙여넣기)'!A3:A562,A14,'외운 것 - 엑셀다운로드 파일(붙여넣기)'!D3:D562,0)} -> 0 | L14: {=IF(J14>=3,_xlfn.XLOOKUP(A14,'외운 것 - 엑셀다운로드 파일(붙여넣기)'!A3:A562,'외운 것 - 엑셀다운로드 파일(붙여넣기)'!C3:C562,0,-1),0)} -> 2026-03-14
A15: 14 | B15: bloat | C15: bl | D15: bl | E15: [blout] | F15: 부풀어(bl) 둥근(o) 모양이 한점(at) 생기니 ‘부풀다(붓다)’ | G15: 부풀다(붓다) | H15: Eating too fast can cause your stomach to bloat. | I15: {=SUBSTITUTE(H15,B15,"( )")} -> Eating too fast can cause your stomach to ( ). | J15: {=SUMIF('외운 것 - 엑셀다운로드 파일(붙여넣기)'!A3:A562,A15,'외운 것 - 엑셀다운로드 파일(붙여넣기)'!D3:D562)} -> 3 | K15: {=_xlfn.COUNTIFS('외운 것 - 엑셀다운로드 파일(붙여넣기)'!A3:A562,A15,'외운 것 - 엑셀다운로드 파일(붙여넣기)'!D3:D562,0)} -> 0 | L15: {=IF(J15>=3,_xlfn.XLOOKUP(A15,'외운 것 - 엑셀다운로드 파일(붙여넣기)'!A3:A562,'외운 것 - 엑셀다운로드 파일(붙여넣기)'!C3:C562,0,-1),0)} -> 2026-03-14
A16: 15 | B16: blow | C16: bl | D16: bl | E16: [blou] | F16: 부풀려진(bl) 둥근(o) 입에서 바람(w)을 ‘불다’ | G16: 불다 | H16: The wind will blow strongly tonight. | I16: {=SUBSTITUTE(H16,B16,"( )")} -> The wind will ( ) strongly tonight. | J16: {=SUMIF('외운 것 - 엑셀다운로드 파일(붙여넣기)'!A3:A562,A16,'외운 것 - 엑셀다운로드 파일(붙여넣기)'!D3:D562)} -> 3 | K16: {=_xlfn.COUNTIFS('외운 것 - 엑셀다운로드 파일(붙여넣기)'!A3:A562,A16,'외운 것 - 엑셀다운로드 파일(붙여넣기)'!D3:D562,0)} -> 0 | L16: {=IF(J16>=3,_xlfn.XLOOKUP(A16,'외운 것 - 엑셀다운로드 파일(붙여넣기)'!A3:A562,'외운 것 - 엑셀다운로드 파일(붙여넣기)'!C3:C562,0,-1),0)} -> 2026-03-14
A17: 16 | B17: blowfish | C17: bl > blow | D17: bl | E17: [blóufìꭍ] | F17: 바람을 부는(blow) 것처럼 몸이 부푼 모습의 불고기(fish), ‘복어’ | G17: 복어 | H17: The blowfish can expand to twice its normal size. | I17: {=SUBSTITUTE(H17,B17,"( )")} -> The ( ) can expand to twice its normal size. | J17: {=SUMIF('외운 것 - 엑셀다운로드 파일(붙여넣기)'!A3:A562,A17,'외운 것 - 엑셀다운로드 파일(붙여넣기)'!D3:D562)} -> 3 | K17: {=_xlfn.COUNTIFS('외운 것 - 엑셀다운로드 파일(붙여넣기)'!A3:A562,A17,'외운 것 - 엑셀다운로드 파일(붙여넣기)'!D3:D562,0)} -> 0 | L17: {=IF(J17>=3,_xlfn.XLOOKUP(A17,'외운 것 - 엑셀다운로드 파일(붙여넣기)'!A3:A562,'외운 것 - 엑셀다운로드 파일(붙여넣기)'!C3:C562,0,-1),0)} -> 2026-03-14
A18: 17 | B18: blister | C18: bl | D18: bl | E18: [blístər] | F18: 부풀고(bl) 안에(i) 물이 있어 피부가 서 있는(st) 것처럼 보이는 ‘물집’ | G18: 물집 | H18: I got a blister on my heel from my new shoes. | I18: {=SUBSTITUTE(H18,B18,"( )")} -> I got a ( ) on my heel from my new shoes. | J18: {=SUMIF('외운 것 - 엑셀다운로드 파일(붙여넣기)'!A3:A562,A18,'외운 것 - 엑셀다운로드 파일(붙여넣기)'!D3:D562)} -> 3 | K18: {=_xlfn.COUNTIFS('외운 것 - 엑셀다운로드 파일(붙여넣기)'!A3:A562,A18,'외운 것 - 엑셀다운로드 파일(붙여넣기)'!D3:D562,0)} -> 0 | L18: {=IF(J18>=3,_xlfn.XLOOKUP(A18,'외운 것 - 엑셀다운로드 파일(붙여넣기)'!A3:A562,'외운 것 - 엑셀다운로드 파일(붙여넣기)'!C3:C562,0,-1),0)} -> 2026-03-14
A19: 18 | B19: blur | C19: bl | D19: bl | E19: [bləːr] | F19: 눈꺼풀이부풀어(bl) 올라 시력이 아래로(u) 바닥이 되고 보려면 눈에 힘(r)도 많이 들어가니, ‘흐릿해지다’ | G19: 흐릿해지다 | H19: Her vision became a blur without her glasses. | I19: {=SUBSTITUTE(H19,B19,"( )")} -> Her vision became a ( ) without her glasses. | J19: {=SUMIF('외운 것 - 엑셀다운로드 파일(붙여넣기)'!A3:A562,A19,'외운 것 - 엑셀다운로드 파일(붙여넣기)'!D3:D562)} -> 3 | K19: {=_xlfn.COUNTIFS('외운 것 - 엑셀다운로드 파일(붙여넣기)'!A3:A562,A19,'외운 것 - 엑셀다운로드 파일(붙여넣기)'!D3:D562,0)} -> 0 | L19: {=IF(J19>=3,_xlfn.XLOOKUP(A19,'외운 것 - 엑셀다운로드 파일(붙여넣기)'!A3:A562,'외운 것 - 엑셀다운로드 파일(붙여넣기)'!C3:C562,0,-1),0)} -> 2026-03-14
A20: 19 | B20: blind | C20: bl | D20: bl | E20: [blaind] | F20: 눈꺼풀이 부풀어(bl) 올라 안에(i) 있는 시력을 없어지니(n) ‘눈이 먼’ | G20: 눈이 먼 | H20: The blind man navigated with his white cane. | I20: {=SUBSTITUTE(H20,B20,"( )")} -> The ( ) man navigated with his white cane. | J20: {=SUMIF('외운 것 - 엑셀다운로드 파일(붙여넣기)'!A3:A562,A20,'외운 것 - 엑셀다운로드 파일(붙여넣기)'!D3:D562)} -> 3 | K20: {=_xlfn.COUNTIFS('외운 것 - 엑셀다운로드 파일(붙여넣기)'!A3:A562,A20,'외운 것 - 엑셀다운로드 파일(붙여넣기)'!D3:D562,0)} -> 0 | L20: {=IF(J20>=3,_xlfn.XLOOKUP(A20,'외운 것 - 엑셀다운로드 파일(붙여넣기)'!A3:A562,'외운 것 - 엑셀다운로드 파일(붙여넣기)'!C3:C562,0,-1),0)} -> 2026-03-14
A21: 20 | B21: bluff | C21: bl | D21: bl | E21: [blʌf] | F21: 사실을 부풀려(bl)서 수준이 낮고(u) 내용은 가벼운(ff) ‘허풍’ | G21: 허풍 | H21: His bluff didn't work because everyone knew he was lying. | I21: {=SUBSTITUTE(H21,B21,"( )")} -> His ( ) didn't work because everyone knew he was lying. | J21: {=SUMIF('외운 것 - 엑셀다운로드 파일(붙여넣기)'!A3:A562,A21,'외운 것 - 엑셀다운로드 파일(붙여넣기)'!D3:D562)} -> 3 | K21: {=_xlfn.COUNTIFS('외운 것 - 엑셀다운로드 파일(붙여넣기)'!A3:A562,A21,'외운 것 - 엑셀다운로드 파일(붙여넣기)'!D3:D562,0)} -> 0 | L21: {=IF(J21>=3,_xlfn.XLOOKUP(A21,'외운 것 - 엑셀다운로드 파일(붙여넣기)'!A3:A562,'외운 것 - 엑셀다운로드 파일(붙여넣기)'!C3:C562,0,-1),0)} -> 2026-03-14
A22: 21 | B22: bubble | C22: bu | D22: bu | E22: [bΛbl] | F22: 부풀어(b) 아래에서(u) 올라오며 계속 부풀어(bb) 오르는 ‘거품’ | G22: 거품 | H22: The child laughed as she blew a large soap bubble. | I22: {=SUBSTITUTE(H22,B22,"( )")} -> The child laughed as she blew a large soap ( ). | J22: {=SUMIF('외운 것 - 엑셀다운로드 파일(붙여넣기)'!A3:A562,A22,'외운 것 - 엑셀다운로드 파일(붙여넣기)'!D3:D562)} -> 3 | K22: {=_xlfn.COUNTIFS('외운 것 - 엑셀다운로드 파일(붙여넣기)'!A3:A562,A22,'외운 것 - 엑셀다운로드 파일(붙여넣기)'!D3:D562,0)} -> 0 | L22: {=IF(J22>=3,_xlfn.XLOOKUP(A22,'외운 것 - 엑셀다운로드 파일(붙여넣기)'!A3:A562,'외운 것 - 엑셀다운로드 파일(붙여넣기)'!C3:C562,0,-1),0)} -> 2026-03-14
A23: 22 | B23: bud | C23: bu | D23: bu | E23: [bʌd] | F23: 부풀어 오르지만(bu) 아직 성장이 저하된(d) ‘싹, 꽃봉오리’ | G23: 싹, 꽃봉오리 | H23: The flower bud will soon bloom in spring. | I23: {=SUBSTITUTE(H23,B23,"( )")} -> The flower ( ) will soon bloom in spring. | J23: {=SUMIF('외운 것 - 엑셀다운로드 파일(붙여넣기)'!A3:A562,A23,'외운 것 - 엑셀다운로드 파일(붙여넣기)'!D3:D562)} -> 3 | K23: {=_xlfn.COUNTIFS('외운 것 - 엑셀다운로드 파일(붙여넣기)'!A3:A562,A23,'외운 것 - 엑셀다운로드 파일(붙여넣기)'!D3:D562,0)} -> 0 | L23: {=IF(J23>=3,_xlfn.XLOOKUP(A23,'외운 것 - 엑셀다운로드 파일(붙여넣기)'!A3:A562,'외운 것 - 엑셀다운로드 파일(붙여넣기)'!C3:C562,0,-1),0)} -> 2026-03-14
A24: 23 | B24: budget | C24: bu > bud | D24: bu | E24: [bΛdʒit] | F24: 싹(bud)을 틔우기 위해 가지는(get) ‘예산’ | G24: 예산 | H24: We need to create a budget for our vacation. | I24: {=SUBSTITUTE(H24,B24,"( )")} -> We need to create a ( ) for our vacation. | J24: {=SUMIF('외운 것 - 엑셀다운로드 파일(붙여넣기)'!A3:A562,A24,'외운 것 - 엑셀다운로드 파일(붙여넣기)'!D3:D562)} -> 3 | K24: {=_xlfn.COUNTIFS('외운 것 - 엑셀다운로드 파일(붙여넣기)'!A3:A562,A24,'외운 것 - 엑셀다운로드 파일(붙여넣기)'!D3:D562,0)} -> 1 | L24: {=IF(J24>=3,_xlfn.XLOOKUP(A24,'외운 것 - 엑셀다운로드 파일(붙여넣기)'!A3:A562,'외운 것 - 엑셀다운로드 파일(붙여넣기)'!C3:C562,0,-1),0)} -> 2026-03-16
A25: 24 | B25: bun | C25: bu | D25: bu | E25: [bʌn] | F25: 부풀어 오른(bu) 작은(n) 빵, ‘동그랗고 작은 빵’ | G25: 동그랗고 작은 빵 | H25: She tied her hair in a neat bun for the dance recital. | I25: {=SUBSTITUTE(H25,B25,"( )")} -> She tied her hair in a neat ( ) for the dance recital. | J25: {=SUMIF('외운 것 - 엑셀다운로드 파일(붙여넣기)'!A3:A562,A25,'외운 것 - 엑셀다운로드 파일(붙여넣기)'!D3:D562)} -> 3 | K25: {=_xlfn.COUNTIFS('외운 것 - 엑셀다운로드 파일(붙여넣기)'!A3:A562,A25,'외운 것 - 엑셀다운로드 파일(붙여넣기)'!D3:D562,0)} -> 0 | L25: {=IF(J25>=3,_xlfn.XLOOKUP(A25,'외운 것 - 엑셀다운로드 파일(붙여넣기)'!A3:A562,'외운 것 - 엑셀다운로드 파일(붙여넣기)'!C3:C562,0,-1),0)} -> 2026-03-14
A26: 25 | B26: bunch | C26: bu > bun | D26: bu | E26: [bʌnʧ] | F26: 동그랗고 작은 빵(bun) 같은 것들을 잡아서(ch) 만든 ‘다발, (포도 따위의) 송이’ | G26: 다발, (포도 따위의) 송이 | H26: He brought a bunch of red roses for our anniversary. | I26: {=SUBSTITUTE(H26,B26,"( )")} -> He brought a ( ) of red roses for our anniversary. | J26: {=SUMIF('외운 것 - 엑셀다운로드 파일(붙여넣기)'!A3:A562,A26,'외운 것 - 엑셀다운로드 파일(붙여넣기)'!D3:D562)} -> 3 | K26: {=_xlfn.COUNTIFS('외운 것 - 엑셀다운로드 파일(붙여넣기)'!A3:A562,A26,'외운 것 - 엑셀다운로드 파일(붙여넣기)'!D3:D562,0)} -> 0 | L26: {=IF(J26>=3,_xlfn.XLOOKUP(A26,'외운 것 - 엑셀다운로드 파일(붙여넣기)'!A3:A562,'외운 것 - 엑셀다운로드 파일(붙여넣기)'!C3:C562,0,-1),0)} -> 2026-03-14
A27: 26 | B27: buy | C27: bu | D27: bu | E27: [bai] | F27: 자꾸 ‘사다’ 그래서 가방이 부풀어 오르고(bu) 안에 구입한 개수가 확장(y)되어 간다. | G27: 사다 | H27: I want to buy a new computer next month. | I27: {=SUBSTITUTE(H27,B27,"( )")} -> I want to ( ) a new computer next month. | J27: {=SUMIF('외운 것 - 엑셀다운로드 파일(붙여넣기)'!A3:A562,A27,'외운 것 - 엑셀다운로드 파일(붙여넣기)'!D3:D562)} -> 3 | K27: {=_xlfn.COUNTIFS('외운 것 - 엑셀다운로드 파일(붙여넣기)'!A3:A562,A27,'외운 것 - 엑셀다운로드 파일(붙여넣기)'!D3:D562,0)} -> 0 | L27: {=IF(J27>=3,_xlfn.XLOOKUP(A27,'외운 것 - 엑셀다운로드 파일(붙여넣기)'!A3:A562,'외운 것 - 엑셀다운로드 파일(붙여넣기)'!C3:C562,0,-1),0)} -> 2026-03-14
A28: 27 | B28: bury | C28: bu > buy | D28: bu | E28: [béri] | F28: 사서(buy) 세게 힘을(r) 가해 ‘묻어 놓다’ | G28: 묻어 놓다 | H28: They will bury the time capsule in the school yard. | I28: {=SUBSTITUTE(H28,B28,"( )")} -> They will ( ) the time capsule in the school yard. | J28: {=SUMIF('외운 것 - 엑셀다운로드 파일(붙여넣기)'!A3:A562,A28,'외운 것 - 엑셀다운로드 파일(붙여넣기)'!D3:D562)} -> 1 | K28: {=_xlfn.COUNTIFS('외운 것 - 엑셀다운로드 파일(붙여넣기)'!A3:A562,A28,'외운 것 - 엑셀다운로드 파일(붙여넣기)'!D3:D562,0)} -> 4 | L28: {=IF(J28>=3,_xlfn.XLOOKUP(A28,'외운 것 - 엑셀다운로드 파일(붙여넣기)'!A3:A562,'외운 것 - 엑셀다운로드 파일(붙여넣기)'!C3:C562,0,-1),0)} -> 0
A29: 28 | B29: burp | C29: bu | D29: bu | E29: [bəːrp] | F29: 속에서 부풀어 올라오는(bu) 가스의 힘(r)이 밖으로 폭하고(p) 튀어 나오는 ‘트림, 트림소리’ | G29: 트림, 트림소리 | H29: The baby needs to burp after drinking milk. | I29: {=SUBSTITUTE(H29,B29,"( )")} -> The baby needs to ( ) after drinking milk. | J29: {=SUMIF('외운 것 - 엑셀다운로드 파일(붙여넣기)'!A3:A562,A29,'외운 것 - 엑셀다운로드 파일(붙여넣기)'!D3:D562)} -> 3 | K29: {=_xlfn.COUNTIFS('외운 것 - 엑셀다운로드 파일(붙여넣기)'!A3:A562,A29,'외운 것 - 엑셀다운로드 파일(붙여넣기)'!D3:D562,0)} -> 0 | L29: {=IF(J29>=3,_xlfn.XLOOKUP(A29,'외운 것 - 엑셀다운로드 파일(붙여넣기)'!A3:A562,'외운 것 - 엑셀다운로드 파일(붙여넣기)'!C3:C562,0,-1),0)} -> 2026-03-14
A30: 29 | B30: ban | C30: b | D30: ban | E30: [bæn] | F30: 막고(b) 하나(an)도 못 나가게 하니 ‘막다, 금지하다, 금지’ | G30: 막다, 금지하다, 금지 | H30: The school decided to ban mobile phones during class. | I30: {=SUBSTITUTE(H30,B30,"( )")} -> The school decided to ( ) mobile phones during class. | J30: {=SUMIF('외운 것 - 엑셀다운로드 파일(붙여넣기)'!A3:A562,A30,'외운 것 - 엑셀다운로드 파일(붙여넣기)'!D3:D562)} -> 3 | K30: {=_xlfn.COUNTIFS('외운 것 - 엑셀다운로드 파일(붙여넣기)'!A3:A562,A30,'외운 것 - 엑셀다운로드 파일(붙여넣기)'!D3:D562,0)} -> 0 | L30: {=IF(J30>=3,_xlfn.XLOOKUP(A30,'외운 것 - 엑셀다운로드 파일(붙여넣기)'!A3:A562,'외운 것 - 엑셀다운로드 파일(붙여넣기)'!C3:C562,0,-1),0)} -> 2026-03-14
A31: 30 | B31: banish | C31: b > ban | D31: ban | E31: [bǽniʃ] | F31: 들어오는 걸 막고(ban) 보이지(sh) 않도록 ‘추방하다, 몰아내다’ | G31: 추방하다, 몰아내다 | H31: The king will banish anyone who breaks the law. | I31: {=SUBSTITUTE(H31,B31,"( )")} -> The king will ( ) anyone who breaks the law. | J31: {=SUMIF('외운 것 - 엑셀다운로드 파일(붙여넣기)'!A3:A562,A31,'외운 것 - 엑셀다운로드 파일(붙여넣기)'!D3:D562)} -> 3 | K31: {=_xlfn.COUNTIFS('외운 것 - 엑셀다운로드 파일(붙여넣기)'!A3:A562,A31,'외운 것 - 엑셀다운로드 파일(붙여넣기)'!D3:D562,0)} -> 0 | L31: {=IF(J31>=3,_xlfn.XLOOKUP(A31,'외운 것 - 엑셀다운로드 파일(붙여넣기)'!A3:A562,'외운 것 - 엑셀다운로드 파일(붙여넣기)'!C3:C562,0,-1),0)} -> 2026-03-14
A32: 31 | B32: band | C32: b | D32: ban | E32: [bænd] | F32: 터져 나가지 못하게 막으려고(b) 끈을 더하여(and) ‘묶다, 반창고, 띠, 무리’ | G32: 묶다, 반창고, 띠, 무리 | H32: My favorite band is performing at the concert tonight. | I32: {=SUBSTITUTE(H32,B32,"( )")} -> My favorite ( ) is performing at the concert tonight. | J32: {=SUMIF('외운 것 - 엑셀다운로드 파일(붙여넣기)'!A3:A562,A32,'외운 것 - 엑셀다운로드 파일(붙여넣기)'!D3:D562)} -> 3 | K32: {=_xlfn.COUNTIFS('외운 것 - 엑셀다운로드 파일(붙여넣기)'!A3:A562,A32,'외운 것 - 엑셀다운로드 파일(붙여넣기)'!D3:D562,0)} -> 0 | L32: {=IF(J32>=3,_xlfn.XLOOKUP(A32,'외운 것 - 엑셀다운로드 파일(붙여넣기)'!A3:A562,'외운 것 - 엑셀다운로드 파일(붙여넣기)'!C3:C562,0,-1),0)} -> 2026-03-14
A33: 32 | B33: bandit | C33: band | D33: band | E33: [bǽndit] | F33: 묶어 놓고(band) 그것(it)을 달라고 하는 ‘노상강도’ | G33: 노상강도 | H33: The bandit stole money from the stagecoach. | I33: {=SUBSTITUTE(H33,B33,"( )")} -> The ( ) stole money from the stagecoach. | J33: {=SUMIF('외운 것 - 엑셀다운로드 파일(붙여넣기)'!A3:A562,A33,'외운 것 - 엑셀다운로드 파일(붙여넣기)'!D3:D562)} -> 3 | K33: {=_xlfn.COUNTIFS('외운 것 - 엑셀다운로드 파일(붙여넣기)'!A3:A562,A33,'외운 것 - 엑셀다운로드 파일(붙여넣기)'!D3:D562,0)} -> 0 | L33: {=IF(J33>=3,_xlfn.XLOOKUP(A33,'외운 것 - 엑셀다운로드 파일(붙여넣기)'!A3:A562,'외운 것 - 엑셀다운로드 파일(붙여넣기)'!C3:C562,0,-1),0)} -> 2026-03-14
A34: 33 | B34: husband | C34: band | D34: band | E34: [hΛzbənd] | F34: 집(house)을 끈(band)으로 둘러싸듯 보호하는 사람, ‘남편’ | G34: 남편 | H34: Her husband cooks dinner every Friday night. | I34: {=SUBSTITUTE(H34,B34,"( )")} -> Her ( ) cooks dinner every Friday night. | J34: {=SUMIF('외운 것 - 엑셀다운로드 파일(붙여넣기)'!A3:A562,A34,'외운 것 - 엑셀다운로드 파일(붙여넣기)'!D3:D562)} -> 3 | K34: {=_xlfn.COUNTIFS('외운 것 - 엑셀다운로드 파일(붙여넣기)'!A3:A562,A34,'외운 것 - 엑셀다운로드 파일(붙여넣기)'!D3:D562,0)} -> 2 | L34: {=IF(J34>=3,_xlfn.XLOOKUP(A34,'외운 것 - 엑셀다운로드 파일(붙여넣기)'!A3:A562,'외운 것 - 엑셀다운로드 파일(붙여넣기)'!C3:C562,0,-1),0)} -> 2026-03-17
A35: 34 | B35: abandon | C35: band | D35: band | E35: [əbǽndən] | F35: 하나로(a) 묶어 놓은(band) 것을 없애니(n) ‘포기하다, 버리다’ | G35: 포기하다, 버리다 | H35: The crew had to abandon the sinking ship. | I35: {=SUBSTITUTE(H35,B35,"( )")} -> The crew had to ( ) the sinking ship. | J35: {=SUMIF('외운 것 - 엑셀다운로드 파일(붙여넣기)'!A3:A562,A35,'외운 것 - 엑셀다운로드 파일(붙여넣기)'!D3:D562)} -> 3 | K35: {=_xlfn.COUNTIFS('외운 것 - 엑셀다운로드 파일(붙여넣기)'!A3:A562,A35,'외운 것 - 엑셀다운로드 파일(붙여넣기)'!D3:D562,0)} -> 1 | L35: {=IF(J35>=3,_xlfn.XLOOKUP(A35,'외운 것 - 엑셀다운로드 파일(붙여넣기)'!A3:A562,'외운 것 - 엑셀다운로드 파일(붙여넣기)'!C3:C562,0,-1),0)} -> 2026-03-16
A36: 35 | B36: bandage | C36: band | D36: band | E36: [bǽndidʒ] | F36: 반창고(band)를 오랫동안(age) 감아 놓으려고 만든 것, ‘붕대’ | G36: 붕대 | H36: The nurse put a bandage on my cut. | I36: {=SUBSTITUTE(H36,B36,"( )")} -> The nurse put a ( ) on my cut. | J36: {=SUMIF('외운 것 - 엑셀다운로드 파일(붙여넣기)'!A3:A562,A36,'외운 것 - 엑셀다운로드 파일(붙여넣기)'!D3:D562)} -> 3 | K36: {=_xlfn.COUNTIFS('외운 것 - 엑셀다운로드 파일(붙여넣기)'!A3:A562,A36,'외운 것 - 엑셀다운로드 파일(붙여넣기)'!D3:D562,0)} -> 0 | L36: {=IF(J36>=3,_xlfn.XLOOKUP(A36,'외운 것 - 엑셀다운로드 파일(붙여넣기)'!A3:A562,'외운 것 - 엑셀다운로드 파일(붙여넣기)'!C3:C562,0,-1),0)} -> 2026-03-14
A37: 36 | B37: bind | C37: band | D37: band | E37: [baind] | F37: (band ▶︎ bind) ‘묶다’ | G37: 묶다 | H37: Strong rope will bind the packages together securely. | I37: {=SUBSTITUTE(H37,B37,"( )")} -> Strong rope will ( ) the packages together securely. | J37: {=SUMIF('외운 것 - 엑셀다운로드 파일(붙여넣기)'!A3:A562,A37,'외운 것 - 엑셀다운로드 파일(붙여넣기)'!D3:D562)} -> 3 | K37: {=_xlfn.COUNTIFS('외운 것 - 엑셀다운로드 파일(붙여넣기)'!A3:A562,A37,'외운 것 - 엑셀다운로드 파일(붙여넣기)'!D3:D562,0)} -> 0 | L37: {=IF(J37>=3,_xlfn.XLOOKUP(A37,'외운 것 - 엑셀다운로드 파일(붙여넣기)'!A3:A562,'외운 것 - 엑셀다운로드 파일(붙여넣기)'!C3:C562,0,-1),0)} -> 2026-03-14
A38: 37 | B38: bond | C38: band | D38: band | E38: [band] | F38: 묶어서(band ▶︎ bond) 하나되게 하는 ‘결속, 유대, 접찹제’ | G38: 결속, 유대, 접찹제 | H38: The mother and child share a special bond. | I38: {=SUBSTITUTE(H38,B38,"( )")} -> The mother and child share a special ( ). | J38: {=SUMIF('외운 것 - 엑셀다운로드 파일(붙여넣기)'!A3:A562,A38,'외운 것 - 엑셀다운로드 파일(붙여넣기)'!D3:D562)} -> 3 | K38: {=_xlfn.COUNTIFS('외운 것 - 엑셀다운로드 파일(붙여넣기)'!A3:A562,A38,'외운 것 - 엑셀다운로드 파일(붙여넣기)'!D3:D562,0)} -> 1 | L38: {=IF(J38>=3,_xlfn.XLOOKUP(A38,'외운 것 - 엑셀다운로드 파일(붙여넣기)'!A3:A562,'외운 것 - 엑셀다운로드 파일(붙여넣기)'!C3:C562,0,-1),0)} -> 2026-03-16
A39: 38 | B39: bound | C39: band > bond | D39: band | E39: [baund] | F39: 아래쪽에(u) 넣어두고 묶으니(bond) 이동이 제한되어 생기는 ‘한계, 경계’ | G39: 한계, 경계 | H39: The rabbit bound across the field quickly. | I39: {=SUBSTITUTE(H39,B39,"( )")} -> The rabbit ( ) across the field quickly. | J39: {=SUMIF('외운 것 - 엑셀다운로드 파일(붙여넣기)'!A3:A562,A39,'외운 것 - 엑셀다운로드 파일(붙여넣기)'!D3:D562)} -> 3 | K39: {=_xlfn.COUNTIFS('외운 것 - 엑셀다운로드 파일(붙여넣기)'!A3:A562,A39,'외운 것 - 엑셀다운로드 파일(붙여넣기)'!D3:D562,0)} -> 0 | L39: {=IF(J39>=3,_xlfn.XLOOKUP(A39,'외운 것 - 엑셀다운로드 파일(붙여넣기)'!A3:A562,'외운 것 - 엑셀다운로드 파일(붙여넣기)'!C3:C562,0,-1),0)} -> 2026-03-14
A40: 39 | B40: boundary | C40: band > bond > bound | D40: band | E40: [báundəri] | F40: 국가 사이의 경계(bound)를 더 강화(r)하고 확장(y)하면 생기는 ‘국경, 경계’ | G40: 국경, 경계 | H40: The fence marks the boundary between the two properties. | I40: {=SUBSTITUTE(H40,B40,"( )")} -> The fence marks the ( ) between the two properties. | J40: {=SUMIF('외운 것 - 엑셀다운로드 파일(붙여넣기)'!A3:A562,A40,'외운 것 - 엑셀다운로드 파일(붙여넣기)'!D3:D562)} -> 3 | K40: {=_xlfn.COUNTIFS('외운 것 - 엑셀다운로드 파일(붙여넣기)'!A3:A562,A40,'외운 것 - 엑셀다운로드 파일(붙여넣기)'!D3:D562,0)} -> 0 | L40: {=IF(J40>=3,_xlfn.XLOOKUP(A40,'외운 것 - 엑셀다운로드 파일(붙여넣기)'!A3:A562,'외운 것 - 엑셀다운로드 파일(붙여넣기)'!C3:C562,0,-1),0)} -> 2026-03-14
A41: 40 | B41: bundle | C41: band > bund | D41: band | E41: [bΛndl] | F41: 묶어서(bund) 긴(l) 끝으로 조이니 만들어지는 ‘다발, 꾸러미’ | G41: 다발, 꾸러미 | H41: She wrapped the baby in a bundle of warm blankets. | I41: {=SUBSTITUTE(H41,B41,"( )")} -> She wrapped the baby in a ( ) of warm blankets. | J41: {=SUMIF('외운 것 - 엑셀다운로드 파일(붙여넣기)'!A3:A562,A41,'외운 것 - 엑셀다운로드 파일(붙여넣기)'!D3:D562)} -> 3 | K41: {=_xlfn.COUNTIFS('외운 것 - 엑셀다운로드 파일(붙여넣기)'!A3:A562,A41,'외운 것 - 엑셀다운로드 파일(붙여넣기)'!D3:D562,0)} -> 0 | L41: {=IF(J41>=3,_xlfn.XLOOKUP(A41,'외운 것 - 엑셀다운로드 파일(붙여넣기)'!A3:A562,'외운 것 - 엑셀다운로드 파일(붙여넣기)'!C3:C562,0,-1),0)} -> 2026-03-14
A42: 41 | B42: bar | C42: b | D42: bar | E42: [baːr] | F42: 막는데(b) 막대기 같은 것을 더해(a) 힘을(r) 가하니 ‘가로막다, 빗장, 막대기’ | G42: 가로막다, 빗장, 막대기 | H42: Let's meet at the coffee bar after work. | I42: {=SUBSTITUTE(H42,B42,"( )")} -> Let's meet at the coffee ( ) after work. | J42: {=SUMIF('외운 것 - 엑셀다운로드 파일(붙여넣기)'!A3:A562,A42,'외운 것 - 엑셀다운로드 파일(붙여넣기)'!D3:D562)} -> 3 | K42: {=_xlfn.COUNTIFS('외운 것 - 엑셀다운로드 파일(붙여넣기)'!A3:A562,A42,'외운 것 - 엑셀다운로드 파일(붙여넣기)'!D3:D562,0)} -> 0 | L42: {=IF(J42>=3,_xlfn.XLOOKUP(A42,'외운 것 - 엑셀다운로드 파일(붙여넣기)'!A3:A562,'외운 것 - 엑셀다운로드 파일(붙여넣기)'!C3:C562,0,-1),0)} -> 2026-03-14
A43: 42 | B43: bartender | C43: bar | D43: bar | E43: [baˈrteˌndər] | F43: 막대기(bar)를 뻗어 놓아(tend) 손님이 더 들어오지 못하게 막고 술을 제조하는 사람(er) ‘바텐더’(이에 bar가 술집이라는 의미가 생김) | G43: 바텐더 | H43: The bartender knew how to make all kinds of drinks. | I43: {=SUBSTITUTE(H43,B43,"( )")} -> The ( ) knew how to make all kinds of drinks. | J43: {=SUMIF('외운 것 - 엑셀다운로드 파일(붙여넣기)'!A3:A562,A43,'외운 것 - 엑셀다운로드 파일(붙여넣기)'!D3:D562)} -> 3 | K43: {=_xlfn.COUNTIFS('외운 것 - 엑셀다운로드 파일(붙여넣기)'!A3:A562,A43,'외운 것 - 엑셀다운로드 파일(붙여넣기)'!D3:D562,0)} -> 0 | L43: {=IF(J43>=3,_xlfn.XLOOKUP(A43,'외운 것 - 엑셀다운로드 파일(붙여넣기)'!A3:A562,'외운 것 - 엑셀다운로드 파일(붙여넣기)'!C3:C562,0,-1),0)} -> 2026-03-14
A44: 43 | B44: bargain | C44: bar | D44: bar | E44: [bάːrgən] | F44: 예전에는 술집(bar)에서 서로 원하는 바를 얻기(gain)위해 ‘흥정, 거래’하기도 했다. | G44: 흥정, 거래 | H44: She found a real bargain at the shoe sale. | I44: {=SUBSTITUTE(H44,B44,"( )")} -> She found a real ( ) at the shoe sale. | J44: {=SUMIF('외운 것 - 엑셀다운로드 파일(붙여넣기)'!A3:A562,A44,'외운 것 - 엑셀다운로드 파일(붙여넣기)'!D3:D562)} -> 0 | K44: {=_xlfn.COUNTIFS('외운 것 - 엑셀다운로드 파일(붙여넣기)'!A3:A562,A44,'외운 것 - 엑셀다운로드 파일(붙여넣기)'!D3:D562,0)} -> 5 | L44: {=IF(J44>=3,_xlfn.XLOOKUP(A44,'외운 것 - 엑셀다운로드 파일(붙여넣기)'!A3:A562,'외운 것 - 엑셀다운로드 파일(붙여넣기)'!C3:C562,0,-1),0)} -> 0
A45: 44 | B45: barn | C45: bar | D45: bar | E45: [baːrn] | F45: 입구를 가로 막아서(bar) 없어지지(n) 않게 보관하는 ‘헛간’ | G45: 헛간 | H45: The farmers keep their animals in the barn during winter. | I45: {=SUBSTITUTE(H45,B45,"( )")} -> The farmers keep their animals in the ( ) during winter. | J45: {=SUMIF('외운 것 - 엑셀다운로드 파일(붙여넣기)'!A3:A562,A45,'외운 것 - 엑셀다운로드 파일(붙여넣기)'!D3:D562)} -> 3 | K45: {=_xlfn.COUNTIFS('외운 것 - 엑셀다운로드 파일(붙여넣기)'!A3:A562,A45,'외운 것 - 엑셀다운로드 파일(붙여넣기)'!D3:D562,0)} -> 0 | L45: {=IF(J45>=3,_xlfn.XLOOKUP(A45,'외운 것 - 엑셀다운로드 파일(붙여넣기)'!A3:A562,'외운 것 - 엑셀다운로드 파일(붙여넣기)'!C3:C562,0,-1),0)} -> 2026-03-14
A46: 45 | B46: barrel | C46: bar | D46: bar | E46: [bǽrəl] | F46: 나가지 못하게 막아(bar) 놓은 입구(e)도 있고 흘러가는(l) 액체가 담겨 있는 ‘불룩한 통’ | G46: 불룩한 통 | H46: We store rainwater in a large barrel outside. | I46: {=SUBSTITUTE(H46,B46,"( )")} -> We store rainwater in a large ( ) outside. | J46: {=SUMIF('외운 것 - 엑셀다운로드 파일(붙여넣기)'!A3:A562,A46,'외운 것 - 엑셀다운로드 파일(붙여넣기)'!D3:D562)} -> 3 | K46: {=_xlfn.COUNTIFS('외운 것 - 엑셀다운로드 파일(붙여넣기)'!A3:A562,A46,'외운 것 - 엑셀다운로드 파일(붙여넣기)'!D3:D562,0)} -> 0 | L46: {=IF(J46>=3,_xlfn.XLOOKUP(A46,'외운 것 - 엑셀다운로드 파일(붙여넣기)'!A3:A562,'외운 것 - 엑셀다운로드 파일(붙여넣기)'!C3:C562,0,-1),0)} -> 2026-03-14
A47: 46 | B47: barrier | C47: bar | D47: bar | E47: [bǽriər] | F47: 빗장, 막대기(bar)를 걸어 안에(i) 있도록 힘을(er) 가하는 것, ‘장애물, 울타리’ | G47: 장애물, 울타리 | H47: Language can be a barrier when traveling abroad. | I47: {=SUBSTITUTE(H47,B47,"( )")} -> Language can be a ( ) when traveling abroad. | J47: {=SUMIF('외운 것 - 엑셀다운로드 파일(붙여넣기)'!A3:A562,A47,'외운 것 - 엑셀다운로드 파일(붙여넣기)'!D3:D562)} -> 3 | K47: {=_xlfn.COUNTIFS('외운 것 - 엑셀다운로드 파일(붙여넣기)'!A3:A562,A47,'외운 것 - 엑셀다운로드 파일(붙여넣기)'!D3:D562,0)} -> 0 | L47: {=IF(J47>=3,_xlfn.XLOOKUP(A47,'외운 것 - 엑셀다운로드 파일(붙여넣기)'!A3:A562,'외운 것 - 엑셀다운로드 파일(붙여넣기)'!C3:C562,0,-1),0)} -> 2026-03-14
A48: 47 | B48: barricade | C48: bar | D48: bar | E48: [bǽrəkèid, -′--'] | F48: 빗장, 막대기(bar)를 설치하여 나오지 못하게 잡고(c) 힘을 저하(d)시키는 ‘방책, 장벽, 바리케이드’ | G48: 방책, 장벽, 바리케이드 | H48: Police set up a barricade around the accident scene. | I48: {=SUBSTITUTE(H48,B48,"( )")} -> Police set up a ( ) around the accident scene. | J48: {=SUMIF('외운 것 - 엑셀다운로드 파일(붙여넣기)'!A3:A562,A48,'외운 것 - 엑셀다운로드 파일(붙여넣기)'!D3:D562)} -> 1 | K48: {=_xlfn.COUNTIFS('외운 것 - 엑셀다운로드 파일(붙여넣기)'!A3:A562,A48,'외운 것 - 엑셀다운로드 파일(붙여넣기)'!D3:D562,0)} -> 4 | L48: {=IF(J48>=3,_xlfn.XLOOKUP(A48,'외운 것 - 엑셀다운로드 파일(붙여넣기)'!A3:A562,'외운 것 - 엑셀다운로드 파일(붙여넣기)'!C3:C562,0,-1),0)} -> 0
A49: 48 | B49: embarrass | C49: bar | D49: bar | E49: [imbǽrəs] | F49: 안에(em) 가두고 빗장(bar)을 걸어 나가지 못하게 해 ‘당황하게 하다’ | G49: 당황하게 하다 | H49: Don't embarrass your sister by showing her baby photos. | I49: {=SUBSTITUTE(H49,B49,"( )")} -> Don't ( ) your sister by showing her baby photos. | J49: {=SUMIF('외운 것 - 엑셀다운로드 파일(붙여넣기)'!A3:A562,A49,'외운 것 - 엑셀다운로드 파일(붙여넣기)'!D3:D562)} -> 3 | K49: {=_xlfn.COUNTIFS('외운 것 - 엑셀다운로드 파일(붙여넣기)'!A3:A562,A49,'외운 것 - 엑셀다운로드 파일(붙여넣기)'!D3:D562,0)} -> 1 | L49: {=IF(J49>=3,_xlfn.XLOOKUP(A49,'외운 것 - 엑셀다운로드 파일(붙여넣기)'!A3:A562,'외운 것 - 엑셀다운로드 파일(붙여넣기)'!C3:C562,0,-1),0)} -> 2026-03-16
A50: 49 | B50: embargo | C50: bar | D50: bar | E50: [imbάːrgou] | F50: 안에(em) 가두고 빗장(bar)을 걸어 가지(go) 못하게 하니, ‘통상금지’ | G50: 통상금지 | H50: The country faced an economic embargo for many years. | I50: {=SUBSTITUTE(H50,B50,"( )")} -> The country faced an economic ( ) for many years. | J50: {=SUMIF('외운 것 - 엑셀다운로드 파일(붙여넣기)'!A3:A562,A50,'외운 것 - 엑셀다운로드 파일(붙여넣기)'!D3:D562)} -> 3 | K50: {=_xlfn.COUNTIFS('외운 것 - 엑셀다운로드 파일(붙여넣기)'!A3:A562,A50,'외운 것 - 엑셀다운로드 파일(붙여넣기)'!D3:D562,0)} -> 2 | L50: {=IF(J50>=3,_xlfn.XLOOKUP(A50,'외운 것 - 엑셀다운로드 파일(붙여넣기)'!A3:A562,'외운 것 - 엑셀다운로드 파일(붙여넣기)'!C3:C562,0,-1),0)} -> 2026-03-17
A51: 50 | B51: barren | C51: bar | D51: bar | E51: [bǽrən] | F51: 막아(bar)버리니 자궁(생명의 탄생지) 안(en)을 ‘불임’의 상태, 땅의 생명을 막아 버리니 ‘불모의, 척박한’ 상태이다. | G51: 불임, 불모의, 척박한 | H51: The barren landscape had no trees or plants. | I51: {=SUBSTITUTE(H51,B51,"( )")} -> The ( ) landscape had no trees or plants. | J51: {=SUMIF('외운 것 - 엑셀다운로드 파일(붙여넣기)'!A3:A562,A51,'외운 것 - 엑셀다운로드 파일(붙여넣기)'!D3:D562)} -> 3 | K51: {=_xlfn.COUNTIFS('외운 것 - 엑셀다운로드 파일(붙여넣기)'!A3:A562,A51,'외운 것 - 엑셀다운로드 파일(붙여넣기)'!D3:D562,0)} -> 1 | L51: {=IF(J51>=3,_xlfn.XLOOKUP(A51,'외운 것 - 엑셀다운로드 파일(붙여넣기)'!A3:A562,'외운 것 - 엑셀다운로드 파일(붙여넣기)'!C3:C562,0,-1),0)} -> 2026-03-16
A52: 51 | B52: bat | C52: b | D52: bat | E52: [bæt] | F52: 터져나가(b) 점(at)으로 접하니 하니, ‘때리다, (공을) 치다’ | G52: 때리다, (공을) 치다 | H52: The baseball player swung the bat and hit a home run. | I52: {=SUBSTITUTE(H52,B52,"( )")} -> The baseball player swung the ( ) and hit a home run. | J52: {=SUMIF('외운 것 - 엑셀다운로드 파일(붙여넣기)'!A3:A562,A52,'외운 것 - 엑셀다운로드 파일(붙여넣기)'!D3:D562)} -> 3 | K52: {=_xlfn.COUNTIFS('외운 것 - 엑셀다운로드 파일(붙여넣기)'!A3:A562,A52,'외운 것 - 엑셀다운로드 파일(붙여넣기)'!D3:D562,0)} -> 0 | L52: {=IF(J52>=3,_xlfn.XLOOKUP(A52,'외운 것 - 엑셀다운로드 파일(붙여넣기)'!A3:A562,'외운 것 - 엑셀다운로드 파일(붙여넣기)'!C3:C562,0,-1),0)} -> 2026-03-14
A53: 52 | B53: battle | C53: bat | D53: bat | E53: [bǽtl] | F53: 서로 때리기(bat)를 오래하는(l) ‘전투, 싸움’ | G53: 전투, 싸움 | H53: The ancient battle took place on this very field. | I53: {=SUBSTITUTE(H53,B53,"( )")} -> The ancient ( ) took place on this very field. | J53: {=SUMIF('외운 것 - 엑셀다운로드 파일(붙여넣기)'!A3:A562,A53,'외운 것 - 엑셀다운로드 파일(붙여넣기)'!D3:D562)} -> 3 | K53: {=_xlfn.COUNTIFS('외운 것 - 엑셀다운로드 파일(붙여넣기)'!A3:A562,A53,'외운 것 - 엑셀다운로드 파일(붙여넣기)'!D3:D562,0)} -> 0 | L53: {=IF(J53>=3,_xlfn.XLOOKUP(A53,'외운 것 - 엑셀다운로드 파일(붙여넣기)'!A3:A562,'외운 것 - 엑셀다운로드 파일(붙여넣기)'!C3:C562,0,-1),0)} -> 2026-03-14
A54: 53 | B54: bate | C54: bat | D54: bat | E54: [beit] | F54: 때려서(bat) 작게 만드니 ‘약하게 하다, 줄이다’ | G54: 약하게 하다, 줄이다 | H54: The fisherman used worms to bate his hook. | I54: {=SUBSTITUTE(H54,B54,"( )")} -> The fisherman used worms to ( ) his hook. | J54: {=SUMIF('외운 것 - 엑셀다운로드 파일(붙여넣기)'!A3:A562,A54,'외운 것 - 엑셀다운로드 파일(붙여넣기)'!D3:D562)} -> 3 | K54: {=_xlfn.COUNTIFS('외운 것 - 엑셀다운로드 파일(붙여넣기)'!A3:A562,A54,'외운 것 - 엑셀다운로드 파일(붙여넣기)'!D3:D562,0)} -> 0 | L54: {=IF(J54>=3,_xlfn.XLOOKUP(A54,'외운 것 - 엑셀다운로드 파일(붙여넣기)'!A3:A562,'외운 것 - 엑셀다운로드 파일(붙여넣기)'!C3:C562,0,-1),0)} -> 2026-03-14
A55: 54 | B55: abate | C55: bat > bate | D55: bat | E55: [əbéit] | F55: 하나씩(a) 줄이니(bate) ‘감소시키다, 줄이다, 완화하다’ | G55: 감소시키다, 줄이다, 완화하다 | H55: The storm will abate by morning. | I55: {=SUBSTITUTE(H55,B55,"( )")} -> The storm will ( ) by morning. | J55: {=SUMIF('외운 것 - 엑셀다운로드 파일(붙여넣기)'!A3:A562,A55,'외운 것 - 엑셀다운로드 파일(붙여넣기)'!D3:D562)} -> 3 | K55: {=_xlfn.COUNTIFS('외운 것 - 엑셀다운로드 파일(붙여넣기)'!A3:A562,A55,'외운 것 - 엑셀다운로드 파일(붙여넣기)'!D3:D562,0)} -> 0 | L55: {=IF(J55>=3,_xlfn.XLOOKUP(A55,'외운 것 - 엑셀다운로드 파일(붙여넣기)'!A3:A562,'외운 것 - 엑셀다운로드 파일(붙여넣기)'!C3:C562,0,-1),0)} -> 2026-03-14
A56: 55 | B56: debate | C56: bat > bate | D56: bat | E56: [dibéit] | F56: 말로 상대방의 사기를 저하시키고(d) 약하게(bate) 하는 논쟁, ‘논쟁하다, 토론하다’ | G56: 논쟁하다, 토론하다 | H56: We had a lively debate about climate change. | I56: {=SUBSTITUTE(H56,B56,"( )")} -> We had a lively ( ) about climate change. | J56: {=SUMIF('외운 것 - 엑셀다운로드 파일(붙여넣기)'!A3:A562,A56,'외운 것 - 엑셀다운로드 파일(붙여넣기)'!D3:D562)} -> 3 | K56: {=_xlfn.COUNTIFS('외운 것 - 엑셀다운로드 파일(붙여넣기)'!A3:A562,A56,'외운 것 - 엑셀다운로드 파일(붙여넣기)'!D3:D562,0)} -> 1 | L56: {=IF(J56>=3,_xlfn.XLOOKUP(A56,'외운 것 - 엑셀다운로드 파일(붙여넣기)'!A3:A562,'외운 것 - 엑셀다운로드 파일(붙여넣기)'!C3:C562,0,-1),0)} -> 2026-03-16
A57: 56 | B57: beat | C57: bat | D57: bat | E57: [biːt] | F57: 때리다(bat)보다 좀 더 발음을 길어지게 발음하면 ‘(아주 세게 계속) 때리다’, 그 결과 상대방을 ‘이기다’ | G57: 때리다, 이기다 | H57: My heart began to beat faster when I saw the test results. | I57: {=SUBSTITUTE(H57,B57,"( )")} -> My heart began to ( ) faster when I saw the test results. | J57: {=SUMIF('외운 것 - 엑셀다운로드 파일(붙여넣기)'!A3:A562,A57,'외운 것 - 엑셀다운로드 파일(붙여넣기)'!D3:D562)} -> 3 | K57: {=_xlfn.COUNTIFS('외운 것 - 엑셀다운로드 파일(붙여넣기)'!A3:A562,A57,'외운 것 - 엑셀다운로드 파일(붙여넣기)'!D3:D562,0)} -> 0 | L57: {=IF(J57>=3,_xlfn.XLOOKUP(A57,'외운 것 - 엑셀다운로드 파일(붙여넣기)'!A3:A562,'외운 것 - 엑셀다운로드 파일(붙여넣기)'!C3:C562,0,-1),0)} -> 2026-03-14
A58: 57 | B58: bicycle | C58: bi | D58: bi | E58: [báisikl] | F58: 두개(bi)의 바퀴(cycle) ‘자전거’ | G58: 자전거 | H58: She rides her bicycle to school every day. | I58: {=SUBSTITUTE(H58,B58,"( )")} -> She rides her ( ) to school every day. | J58: {=SUMIF('외운 것 - 엑셀다운로드 파일(붙여넣기)'!A3:A562,A58,'외운 것 - 엑셀다운로드 파일(붙여넣기)'!D3:D562)} -> 3 | K58: {=_xlfn.COUNTIFS('외운 것 - 엑셀다운로드 파일(붙여넣기)'!A3:A562,A58,'외운 것 - 엑셀다운로드 파일(붙여넣기)'!D3:D562,0)} -> 0 | L58: {=IF(J58>=3,_xlfn.XLOOKUP(A58,'외운 것 - 엑셀다운로드 파일(붙여넣기)'!A3:A562,'외운 것 - 엑셀다운로드 파일(붙여넣기)'!C3:C562,0,-1),0)} -> 2026-03-14
A59: 58 | B59: bias | C59: bi | D59: bi | E59: [báiəs] | F59: 다른 두개(bi)를 같다고(as) 하는 ‘편견’ | G59: 편견 | H59: Try not to show bias when judging the competition. | I59: {=SUBSTITUTE(H59,B59,"( )")} -> Try not to show ( ) when judging the competition. | J59: {=SUMIF('외운 것 - 엑셀다운로드 파일(붙여넣기)'!A3:A562,A59,'외운 것 - 엑셀다운로드 파일(붙여넣기)'!D3:D562)} -> 3 | K59: {=_xlfn.COUNTIFS('외운 것 - 엑셀다운로드 파일(붙여넣기)'!A3:A562,A59,'외운 것 - 엑셀다운로드 파일(붙여넣기)'!D3:D562,0)} -> 0 | L59: {=IF(J59>=3,_xlfn.XLOOKUP(A59,'외운 것 - 엑셀다운로드 파일(붙여넣기)'!A3:A562,'외운 것 - 엑셀다운로드 파일(붙여넣기)'!C3:C562,0,-1),0)} -> 2026-03-14
A60: 59 | B60: alibi | C60: bi | D60: bi | E60: [ǽləbài] | F60: 모두 다(ali-all) 범행 현장과 다른 각각의, 두개의(bi) 장소에 있었음을 증명하는, ‘알리바이, 변명’ | G60: 알리바이, 변명 | H60: The suspect had a strong alibi for the night of the crime. | I60: {=SUBSTITUTE(H60,B60,"( )")} -> The suspect had a strong ( ) for the night of the crime. | J60: {=SUMIF('외운 것 - 엑셀다운로드 파일(붙여넣기)'!A3:A562,A60,'외운 것 - 엑셀다운로드 파일(붙여넣기)'!D3:D562)} -> 3 | K60: {=_xlfn.COUNTIFS('외운 것 - 엑셀다운로드 파일(붙여넣기)'!A3:A562,A60,'외운 것 - 엑셀다운로드 파일(붙여넣기)'!D3:D562,0)} -> 0 | L60: {=IF(J60>=3,_xlfn.XLOOKUP(A60,'외운 것 - 엑셀다운로드 파일(붙여넣기)'!A3:A562,'외운 것 - 엑셀다운로드 파일(붙여넣기)'!C3:C562,0,-1),0)} -> 2026-03-14
A61: 60 | B61: bilingual | C61: bi | D61: bi | E61: [bailíŋgwəl] | F61: 두개(bi)의 언어(language)를 사용하는, ‘2개 국어를 말하는’ | G61: 2개 국어를 말하는 | H61: Being bilingual can help you find better job opportunities. | I61: {=SUBSTITUTE(H61,B61,"( )")} -> Being ( ) can help you find better job opportunities. | J61: {=SUMIF('외운 것 - 엑셀다운로드 파일(붙여넣기)'!A3:A562,A61,'외운 것 - 엑셀다운로드 파일(붙여넣기)'!D3:D562)} -> 3 | K61: {=_xlfn.COUNTIFS('외운 것 - 엑셀다운로드 파일(붙여넣기)'!A3:A562,A61,'외운 것 - 엑셀다운로드 파일(붙여넣기)'!D3:D562,0)} -> 1 | L61: {=IF(J61>=3,_xlfn.XLOOKUP(A61,'외운 것 - 엑셀다운로드 파일(붙여넣기)'!A3:A562,'외운 것 - 엑셀다운로드 파일(붙여넣기)'!C3:C562,0,-1),0)} -> 2026-03-16
A62: 61 | B62: binoculars | C62: bi | D62: bi | E62: [bainάkjulər, bə-] | F62: 두개(bi)의 렌즈(ocular)를 사용하는 ‘쌍안경’ | G62: 쌍안경 | H62: We used binoculars to watch birds at the lake. | I62: {=SUBSTITUTE(H62,B62,"( )")} -> We used ( ) to watch birds at the lake. | J62: {=SUMIF('외운 것 - 엑셀다운로드 파일(붙여넣기)'!A3:A562,A62,'외운 것 - 엑셀다운로드 파일(붙여넣기)'!D3:D562)} -> 2 | K62: {=_xlfn.COUNTIFS('외운 것 - 엑셀다운로드 파일(붙여넣기)'!A3:A562,A62,'외운 것 - 엑셀다운로드 파일(붙여넣기)'!D3:D562,0)} -> 3 | L62: {=IF(J62>=3,_xlfn.XLOOKUP(A62,'외운 것 - 엑셀다운로드 파일(붙여넣기)'!A3:A562,'외운 것 - 엑셀다운로드 파일(붙여넣기)'!C3:C562,0,-1),0)} -> 0
A63: 62 | B63: bisect | C63: bi | D63: bi | E63: [baisékt, -'-] | F63: 두개(bi)로 자르니(sect) ‘양분하다, 이등분하다’ | G63: 양분하다, 이등분하다 | H63: The river bisects the city into north and south regions. | I63: {=SUBSTITUTE(H63,B63,"( )")} -> The river ( )s the city into north and south regions. | J63: {=SUMIF('외운 것 - 엑셀다운로드 파일(붙여넣기)'!A3:A562,A63,'외운 것 - 엑셀다운로드 파일(붙여넣기)'!D3:D562)} -> 3 | K63: {=_xlfn.COUNTIFS('외운 것 - 엑셀다운로드 파일(붙여넣기)'!A3:A562,A63,'외운 것 - 엑셀다운로드 파일(붙여넣기)'!D3:D562,0)} -> 0 | L63: {=IF(J63>=3,_xlfn.XLOOKUP(A63,'외운 것 - 엑셀다운로드 파일(붙여넣기)'!A3:A562,'외운 것 - 엑셀다운로드 파일(붙여넣기)'!C3:C562,0,-1),0)} -> 2026-03-14
A64: 63 | B64: biology | C64: bio | D64: bio | E64: [baiάlədʒi] | F64: 생명(bio)을 다루는 학문(log)인 ‘생물학’ | G64: 생물학 | H64: She studies biology at the university. | I64: {=SUBSTITUTE(H64,B64,"( )")} -> She studies ( ) at the university. | J64: {=SUMIF('외운 것 - 엑셀다운로드 파일(붙여넣기)'!A3:A562,A64,'외운 것 - 엑셀다운로드 파일(붙여넣기)'!D3:D562)} -> 3 | K64: {=_xlfn.COUNTIFS('외운 것 - 엑셀다운로드 파일(붙여넣기)'!A3:A562,A64,'외운 것 - 엑셀다운로드 파일(붙여넣기)'!D3:D562,0)} -> 2 | L64: {=IF(J64>=3,_xlfn.XLOOKUP(A64,'외운 것 - 엑셀다운로드 파일(붙여넣기)'!A3:A562,'외운 것 - 엑셀다운로드 파일(붙여넣기)'!C3:C562,0,-1),0)} -> 2026-03-17
A65: 64 | B65: antibiotic | C65: bio | D65: bio | E65: [ӕntibaiάtik, -tai-] | F65: 반대(anti)로 생명(bio)에 작용하는 ‘항생 물질, 항생제’ | G65: 항생 물질, 항생제 | H65: The doctor prescribed an antibiotic for my infection. | I65: {=SUBSTITUTE(H65,B65,"( )")} -> The doctor prescribed an ( ) for my infection. | J65: {=SUMIF('외운 것 - 엑셀다운로드 파일(붙여넣기)'!A3:A562,A65,'외운 것 - 엑셀다운로드 파일(붙여넣기)'!D3:D562)} -> 1 | K65: {=_xlfn.COUNTIFS('외운 것 - 엑셀다운로드 파일(붙여넣기)'!A3:A562,A65,'외운 것 - 엑셀다운로드 파일(붙여넣기)'!D3:D562,0)} -> 4 | L65: {=IF(J65>=3,_xlfn.XLOOKUP(A65,'외운 것 - 엑셀다운로드 파일(붙여넣기)'!A3:A562,'외운 것 - 엑셀다운로드 파일(붙여넣기)'!C3:C562,0,-1),0)} -> 0
A66: 65 | B66: biography | C66: bio | D66: bio | E66: [baiάgrəfi] | F66: 생명(bio), 인생에 대해 그래프(graph)를 그리듯이 쓴 ‘전기, 일대기’ | G66: 전기, 일대기 | H66: I'm reading a biography about Albert Einstein. | I66: {=SUBSTITUTE(H66,B66,"( )")} -> I'm reading a ( ) about Albert Einstein. | J66: {=SUMIF('외운 것 - 엑셀다운로드 파일(붙여넣기)'!A3:A562,A66,'외운 것 - 엑셀다운로드 파일(붙여넣기)'!D3:D562)} -> 3 | K66: {=_xlfn.COUNTIFS('외운 것 - 엑셀다운로드 파일(붙여넣기)'!A3:A562,A66,'외운 것 - 엑셀다운로드 파일(붙여넣기)'!D3:D562,0)} -> 2 | L66: {=IF(J66>=3,_xlfn.XLOOKUP(A66,'외운 것 - 엑셀다운로드 파일(붙여넣기)'!A3:A562,'외운 것 - 엑셀다운로드 파일(붙여넣기)'!C3:C562,0,-1),0)} -> 2026-03-17
A67: 66 | B67: bloom | C67: bl | D67: bl | E67: [bluːm] | F67: 꽃망울이 터져(bl) 향기가 아래쪽(oo)에서 부터 사방에 움직여(m) 나가니 ‘꽃이 피다’ | G67: 꽃이 피다 | H67: The roses bloom beautifully in our garden each summer. | I67: {=SUBSTITUTE(H67,B67,"( )")} -> The roses ( ) beautifully in our garden each summer. | J67: {=SUMIF('외운 것 - 엑셀다운로드 파일(붙여넣기)'!A3:A562,A67,'외운 것 - 엑셀다운로드 파일(붙여넣기)'!D3:D562)} -> 3 | K67: {=_xlfn.COUNTIFS('외운 것 - 엑셀다운로드 파일(붙여넣기)'!A3:A562,A67,'외운 것 - 엑셀다운로드 파일(붙여넣기)'!D3:D562,0)} -> 0 | L67: {=IF(J67>=3,_xlfn.XLOOKUP(A67,'외운 것 - 엑셀다운로드 파일(붙여넣기)'!A3:A562,'외운 것 - 엑셀다운로드 파일(붙여넣기)'!C3:C562,0,-1),0)} -> 2026-03-14
A68: 67 | B68: black | C68: bl | D68: bl | E68: [blæk] | F68: 빛이 다 터져(bl) 나가고 빛이 부족(lack)해서 깜깜한 상태인 ‘검은, 검은색’ | G68: 검은, 검은색 | H68: She wore a black dress to the formal dinner. | I68: {=SUBSTITUTE(H68,B68,"( )")} -> She wore a ( ) dress to the formal dinner. | J68: {=SUMIF('외운 것 - 엑셀다운로드 파일(붙여넣기)'!A3:A562,A68,'외운 것 - 엑셀다운로드 파일(붙여넣기)'!D3:D562)} -> 3 | K68: {=_xlfn.COUNTIFS('외운 것 - 엑셀다운로드 파일(붙여넣기)'!A3:A562,A68,'외운 것 - 엑셀다운로드 파일(붙여넣기)'!D3:D562,0)} -> 0 | L68: {=IF(J68>=3,_xlfn.XLOOKUP(A68,'외운 것 - 엑셀다운로드 파일(붙여넣기)'!A3:A562,'외운 것 - 엑셀다운로드 파일(붙여넣기)'!C3:C562,0,-1),0)} -> 2026-03-14
A69: 68 | B69: blank | C69: bl | D69: bl | E69: [blæŋk] | F69: 글자가 다 터져(bl) 나가 없어지면서(n) 확장(k)되어 날아가 버리니, ‘비어있는, 백지의, 빈칸’ | G69: 비어있는, 백지의, 빈칸 | H69: Please don't leave any blank spaces on the application form. | I69: {=SUBSTITUTE(H69,B69,"( )")} -> Please don't leave any ( ) spaces on the application form. | J69: {=SUMIF('외운 것 - 엑셀다운로드 파일(붙여넣기)'!A3:A562,A69,'외운 것 - 엑셀다운로드 파일(붙여넣기)'!D3:D562)} -> 3 | K69: {=_xlfn.COUNTIFS('외운 것 - 엑셀다운로드 파일(붙여넣기)'!A3:A562,A69,'외운 것 - 엑셀다운로드 파일(붙여넣기)'!D3:D562,0)} -> 0 | L69: {=IF(J69>=3,_xlfn.XLOOKUP(A69,'외운 것 - 엑셀다운로드 파일(붙여넣기)'!A3:A562,'외운 것 - 엑셀다운로드 파일(붙여넣기)'!C3:C562,0,-1),0)} -> 2026-03-14
A70: 69 | B70: blanket | C70: bl > blank | D70: bl | E70: [blǽŋkit] | F70: 흰색이고(blank) 접촉(t)해서 덮어주는 ‘담요’ | G70: 담요 | H70: The child slept peacefully under a warm blanket. | I70: {=SUBSTITUTE(H70,B70,"( )")} -> The child slept peacefully under a warm ( ). | J70: {=SUMIF('외운 것 - 엑셀다운로드 파일(붙여넣기)'!A3:A562,A70,'외운 것 - 엑셀다운로드 파일(붙여넣기)'!D3:D562)} -> 1 | K70: {=_xlfn.COUNTIFS('외운 것 - 엑셀다운로드 파일(붙여넣기)'!A3:A562,A70,'외운 것 - 엑셀다운로드 파일(붙여넣기)'!D3:D562,0)} -> 4 | L70: {=IF(J70>=3,_xlfn.XLOOKUP(A70,'외운 것 - 엑셀다운로드 파일(붙여넣기)'!A3:A562,'외운 것 - 엑셀다운로드 파일(붙여넣기)'!C3:C562,0,-1),0)} -> 0
A71: 70 | B71: bleach | C71: bl | D71: bl | E71: [bliːʧ] | F71: 색이 터져(bl) 나가게 잡아서(ch) 빼내니 ‘표백하다, 희게하다’ | G71: 표백하다, 희게하다 | H71: Use bleach carefully when washing white clothes. | I71: {=SUBSTITUTE(H71,B71,"( )")} -> Use ( ) carefully when washing white clothes. | J71: {=SUMIF('외운 것 - 엑셀다운로드 파일(붙여넣기)'!A3:A562,A71,'외운 것 - 엑셀다운로드 파일(붙여넣기)'!D3:D562)} -> 3 | K71: {=_xlfn.COUNTIFS('외운 것 - 엑셀다운로드 파일(붙여넣기)'!A3:A562,A71,'외운 것 - 엑셀다운로드 파일(붙여넣기)'!D3:D562,0)} -> 0 | L71: {=IF(J71>=3,_xlfn.XLOOKUP(A71,'외운 것 - 엑셀다운로드 파일(붙여넣기)'!A3:A562,'외운 것 - 엑셀다운로드 파일(붙여넣기)'!C3:C562,0,-1),0)} -> 2026-03-14
A72: 71 | B72: blade | C72: bl | D72: bl | E72: [bleid] | F72: 욱하는 성질이 터져 나와(bl) 아래로(d) 칼을 내려치는 모습에서 연상되는, ‘칼날, 날’ | G72: 칼날, 날 | H72: The knife blade needs to be sharpened. | I72: {=SUBSTITUTE(H72,B72,"( )")} -> The knife ( ) needs to be sharpened. | J72: {=SUMIF('외운 것 - 엑셀다운로드 파일(붙여넣기)'!A3:A562,A72,'외운 것 - 엑셀다운로드 파일(붙여넣기)'!D3:D562)} -> 3 | K72: {=_xlfn.COUNTIFS('외운 것 - 엑셀다운로드 파일(붙여넣기)'!A3:A562,A72,'외운 것 - 엑셀다운로드 파일(붙여넣기)'!D3:D562,0)} -> 0 | L72: {=IF(J72>=3,_xlfn.XLOOKUP(A72,'외운 것 - 엑셀다운로드 파일(붙여넣기)'!A3:A562,'외운 것 - 엑셀다운로드 파일(붙여넣기)'!C3:C562,0,-1),0)} -> 2026-03-14
A73: 72 | B73: bleed | C73: bl | D73: bl | E73: [bliːd] | F73: 상처가 터져서(bl) 벌어진 입구(ee)를 통해 아래로(d) ‘피를 흘리다’ | G73: 피를 흘리다 | H73: His knee started to bleed after he fell off his bike. | I73: {=SUBSTITUTE(H73,B73,"( )")} -> His knee started to ( ) after he fell off his bike. | J73: {=SUMIF('외운 것 - 엑셀다운로드 파일(붙여넣기)'!A3:A562,A73,'외운 것 - 엑셀다운로드 파일(붙여넣기)'!D3:D562)} -> 3 | K73: {=_xlfn.COUNTIFS('외운 것 - 엑셀다운로드 파일(붙여넣기)'!A3:A562,A73,'외운 것 - 엑셀다운로드 파일(붙여넣기)'!D3:D562,0)} -> 0 | L73: {=IF(J73>=3,_xlfn.XLOOKUP(A73,'외운 것 - 엑셀다운로드 파일(붙여넣기)'!A3:A562,'외운 것 - 엑셀다운로드 파일(붙여넣기)'!C3:C562,0,-1),0)} -> 2026-03-14
A74: 73 | B74: blaze | C74: bl | D74: bl | E74: [bleiz] | F74: 터져서 멀리(bl) 불씨가 나가고 지익~(z) 소리를 내며 타다, ‘불타다’ | G74: 불타다 | H74: The forest blaze destroyed thousands of acres. | I74: {=SUBSTITUTE(H74,B74,"( )")} -> The forest ( ) destroyed thousands of acres. | J74: {=SUMIF('외운 것 - 엑셀다운로드 파일(붙여넣기)'!A3:A562,A74,'외운 것 - 엑셀다운로드 파일(붙여넣기)'!D3:D562)} -> 3 | K74: {=_xlfn.COUNTIFS('외운 것 - 엑셀다운로드 파일(붙여넣기)'!A3:A562,A74,'외운 것 - 엑셀다운로드 파일(붙여넣기)'!D3:D562,0)} -> 0 | L74: {=IF(J74>=3,_xlfn.XLOOKUP(A74,'외운 것 - 엑셀다운로드 파일(붙여넣기)'!A3:A562,'외운 것 - 엑셀다운로드 파일(붙여넣기)'!C3:C562,0,-1),0)} -> 2026-03-14
A75: 74 | B75: ablaze | C75: bl > blaze | D75: bl | E75: [əbléiz] | F75: 더하다(a) 불타오는(blaze) 것을 그 결과, ‘불길에 휩싸인’ | G75: 불길에 휩싸인 | H75: The sky was ablaze with colorful fireworks. | I75: {=SUBSTITUTE(H75,B75,"( )")} -> The sky was ( ) with colorful fireworks. | J75: {=SUMIF('외운 것 - 엑셀다운로드 파일(붙여넣기)'!A3:A562,A75,'외운 것 - 엑셀다운로드 파일(붙여넣기)'!D3:D562)} -> 3 | K75: {=_xlfn.COUNTIFS('외운 것 - 엑셀다운로드 파일(붙여넣기)'!A3:A562,A75,'외운 것 - 엑셀다운로드 파일(붙여넣기)'!D3:D562,0)} -> 0 | L75: {=IF(J75>=3,_xlfn.XLOOKUP(A75,'외운 것 - 엑셀다운로드 파일(붙여넣기)'!A3:A562,'외운 것 - 엑셀다운로드 파일(붙여넣기)'!C3:C562,0,-1),0)} -> 2026-03-14
A76: 75 | B76: blizzard | C76: bl > blaze | D76: bl | E76: [blízərd] | F76: 불타는(blaze) 듯이 눈보라가 부니 ‘심한 눈보라, 폭설’ | G76: 심한 눈보라, 폭설 | H76: A blizzard is forecast for this weekend. | I76: {=SUBSTITUTE(H76,B76,"( )")} -> A ( ) is forecast for this weekend. | J76: {=SUMIF('외운 것 - 엑셀다운로드 파일(붙여넣기)'!A3:A562,A76,'외운 것 - 엑셀다운로드 파일(붙여넣기)'!D3:D562)} -> 1 | K76: {=_xlfn.COUNTIFS('외운 것 - 엑셀다운로드 파일(붙여넣기)'!A3:A562,A76,'외운 것 - 엑셀다운로드 파일(붙여넣기)'!D3:D562,0)} -> 4 | L76: {=IF(J76>=3,_xlfn.XLOOKUP(A76,'외운 것 - 엑셀다운로드 파일(붙여넣기)'!A3:A562,'외운 것 - 엑셀다운로드 파일(붙여넣기)'!C3:C562,0,-1),0)} -> 0
A77: 76 | B77: bless | C77: bl | D77: bl | E77: [bles] | F77: 행운이 터져서 멀리(bl) 나가길 바라니 ‘축복하다’ | G77: 축복하다 | H77: May God bless you and your family. | I77: {=SUBSTITUTE(H77,B77,"( )")} -> May God ( ) you and your family. | J77: {=SUMIF('외운 것 - 엑셀다운로드 파일(붙여넣기)'!A3:A562,A77,'외운 것 - 엑셀다운로드 파일(붙여넣기)'!D3:D562)} -> 3 | K77: {=_xlfn.COUNTIFS('외운 것 - 엑셀다운로드 파일(붙여넣기)'!A3:A562,A77,'외운 것 - 엑셀다운로드 파일(붙여넣기)'!D3:D562,0)} -> 0 | L77: {=IF(J77>=3,_xlfn.XLOOKUP(A77,'외운 것 - 엑셀다운로드 파일(붙여넣기)'!A3:A562,'외운 것 - 엑셀다운로드 파일(붙여넣기)'!C3:C562,0,-1),0)} -> 2026-03-14
A78: 77 | B78: blast | C78: bl | D78: bl | E78: [blæst] | F78: 터져서 멀리(bl) 나가게 하니 ‘폭발하다, 폭파’ | G78: 폭발하다, 폭파 | H78: The explosion blast could be heard for miles. | I78: {=SUBSTITUTE(H78,B78,"( )")} -> The explosion ( ) could be heard for miles. | J78: {=SUMIF('외운 것 - 엑셀다운로드 파일(붙여넣기)'!A3:A562,A78,'외운 것 - 엑셀다운로드 파일(붙여넣기)'!D3:D562)} -> 3 | K78: {=_xlfn.COUNTIFS('외운 것 - 엑셀다운로드 파일(붙여넣기)'!A3:A562,A78,'외운 것 - 엑셀다운로드 파일(붙여넣기)'!D3:D562,0)} -> 0 | L78: {=IF(J78>=3,_xlfn.XLOOKUP(A78,'외운 것 - 엑셀다운로드 파일(붙여넣기)'!A3:A562,'외운 것 - 엑셀다운로드 파일(붙여넣기)'!C3:C562,0,-1),0)} -> 2026-03-14
A79: 78 | B79: bluster | C79: bl | D79: bl | E79: [blΛstər] | F79: 파도가 터지듯이(bl) 아래쪽에서(u) 부터 세차져서 서서(st) 힘있게(r) 때리니 ‘(파도가) 거세게 몰아치다, 고함치다’ | G79: (파도가) 거세게 몰아치다, 고함치다 | H79: The politician's bluster didn't convince the voters. | I79: {=SUBSTITUTE(H79,B79,"( )")} -> The politician's ( ) didn't convince the voters. | J79: {=SUMIF('외운 것 - 엑셀다운로드 파일(붙여넣기)'!A3:A562,A79,'외운 것 - 엑셀다운로드 파일(붙여넣기)'!D3:D562)} -> 3 | K79: {=_xlfn.COUNTIFS('외운 것 - 엑셀다운로드 파일(붙여넣기)'!A3:A562,A79,'외운 것 - 엑셀다운로드 파일(붙여넣기)'!D3:D562,0)} -> 1 | L79: {=IF(J79>=3,_xlfn.XLOOKUP(A79,'외운 것 - 엑셀다운로드 파일(붙여넣기)'!A3:A562,'외운 것 - 엑셀다운로드 파일(붙여넣기)'!C3:C562,0,-1),0)} -> 2026-03-16
A80: 79 | B80: burst | C80: b | D80: b | E80: [bəːrst] | F80: 터져서(b) 아래쪽에서(u) 있던 것이 세게(r) 다 나가 서(st) 버리니 ‘폭발하다, 폭발’ | G80: 폭발하다, 폭발 | H80: The balloon will burst if you blow too much air into it. | I80: {=SUBSTITUTE(H80,B80,"( )")} -> The balloon will ( ) if you blow too much air into it. | J80: {=SUMIF('외운 것 - 엑셀다운로드 파일(붙여넣기)'!A3:A562,A80,'외운 것 - 엑셀다운로드 파일(붙여넣기)'!D3:D562)} -> 3 | K80: {=_xlfn.COUNTIFS('외운 것 - 엑셀다운로드 파일(붙여넣기)'!A3:A562,A80,'외운 것 - 엑셀다운로드 파일(붙여넣기)'!D3:D562,0)} -> 1 | L80: {=IF(J80>=3,_xlfn.XLOOKUP(A80,'외운 것 - 엑셀다운로드 파일(붙여넣기)'!A3:A562,'외운 것 - 엑셀다운로드 파일(붙여넣기)'!C3:C562,0,-1),0)} -> 2026-03-16
A81: 80 | B81: blare | C81: bl | D81: bl | E81: [blεər] | F81: 어떤 내용을 크게 터지듯이(bl) 힘있게(r) 말하니 ‘크게 울려 퍼지다’ | G81: 크게 울려 퍼지다 | H81: The car alarms blare was annoying the neighbors. | I81: {=SUBSTITUTE(H81,B81,"( )")} -> The car alarms ( ) was annoying the neighbors. | J81: {=SUMIF('외운 것 - 엑셀다운로드 파일(붙여넣기)'!A3:A562,A81,'외운 것 - 엑셀다운로드 파일(붙여넣기)'!D3:D562)} -> 3 | K81: {=_xlfn.COUNTIFS('외운 것 - 엑셀다운로드 파일(붙여넣기)'!A3:A562,A81,'외운 것 - 엑셀다운로드 파일(붙여넣기)'!D3:D562,0)} -> 1 | L81: {=IF(J81>=3,_xlfn.XLOOKUP(A81,'외운 것 - 엑셀다운로드 파일(붙여넣기)'!A3:A562,'외운 것 - 엑셀다운로드 파일(붙여넣기)'!C3:C562,0,-1),0)} -> 2026-03-16
A82: 81 | B82: blond | C82: bl | D82: bl | E82: [bland] | F82: 빛이 터져 나가는(bl) 눈부신 금색이고 둥근 머리(o) 끝(end-nd)에 나 있는 ‘금발’ | G82: 금발 | H82: Her blond hair shines in the sunlight. | I82: {=SUBSTITUTE(H82,B82,"( )")} -> Her ( ) hair shines in the sunlight. | J82: {=SUMIF('외운 것 - 엑셀다운로드 파일(붙여넣기)'!A3:A562,A82,'외운 것 - 엑셀다운로드 파일(붙여넣기)'!D3:D562)} -> 3 | K82: {=_xlfn.COUNTIFS('외운 것 - 엑셀다운로드 파일(붙여넣기)'!A3:A562,A82,'외운 것 - 엑셀다운로드 파일(붙여넣기)'!D3:D562,0)} -> 1 | L82: {=IF(J82>=3,_xlfn.XLOOKUP(A82,'외운 것 - 엑셀다운로드 파일(붙여넣기)'!A3:A562,'외운 것 - 엑셀다운로드 파일(붙여넣기)'!C3:C562,0,-1),0)} -> 2026-03-16
A83: 82 | B83: break | C83: br | D83: br | E83: [breik] | F83: 터져서(b) 깨진 그 조각들이 힘 차게(r) 확장(k)되어 나가니, ‘깨뜨리다, 부수다’ | G83: 깨뜨리다, 부수다 | H83: Be careful not to break the glass vase. | I83: {=SUBSTITUTE(H83,B83,"( )")} -> Be careful not to ( ) the glass vase. | J83: {=SUMIF('외운 것 - 엑셀다운로드 파일(붙여넣기)'!A3:A562,A83,'외운 것 - 엑셀다운로드 파일(붙여넣기)'!D3:D562)} -> 3 | K83: {=_xlfn.COUNTIFS('외운 것 - 엑셀다운로드 파일(붙여넣기)'!A3:A562,A83,'외운 것 - 엑셀다운로드 파일(붙여넣기)'!D3:D562,0)} -> 0 | L83: {=IF(J83>=3,_xlfn.XLOOKUP(A83,'외운 것 - 엑셀다운로드 파일(붙여넣기)'!A3:A562,'외운 것 - 엑셀다운로드 파일(붙여넣기)'!C3:C562,0,-1),0)} -> 2026-03-14
A84: 83 | B84: breakfast | C84: br > break | D84: br | E84: [brékfəst] | F84: 깨다(break) 저녁 먹고 아침까지의 단식(fast), 즉 일어나서 처음 먹는 ‘아침식사’ | G84: 아침식사 | H84: I usually eat breakfast at 7:30 every morning. | I84: {=SUBSTITUTE(H84,B84,"( )")} -> I usually eat ( ) at 7:30 every morning. | J84: {=SUMIF('외운 것 - 엑셀다운로드 파일(붙여넣기)'!A3:A562,A84,'외운 것 - 엑셀다운로드 파일(붙여넣기)'!D3:D562)} -> 3 | K84: {=_xlfn.COUNTIFS('외운 것 - 엑셀다운로드 파일(붙여넣기)'!A3:A562,A84,'외운 것 - 엑셀다운로드 파일(붙여넣기)'!D3:D562,0)} -> 2 | L84: {=IF(J84>=3,_xlfn.XLOOKUP(A84,'외운 것 - 엑셀다운로드 파일(붙여넣기)'!A3:A562,'외운 것 - 엑셀다운로드 파일(붙여넣기)'!C3:C562,0,-1),0)} -> 2026-03-17
A85: 84 | B85: breakage | C85: br > break | D85: br | E85: [bréikidʒ] | F85: 파괴(break)하여 오래 두니(age) ‘파손, 손상’ | G85: 파손, 손상 | H85: The shipping company is responsible for any breakage during transit. | I85: {=SUBSTITUTE(H85,B85,"( )")} -> The shipping company is responsible for any ( ) during transit. | J85: {=SUMIF('외운 것 - 엑셀다운로드 파일(붙여넣기)'!A3:A562,A85,'외운 것 - 엑셀다운로드 파일(붙여넣기)'!D3:D562)} -> 0 | K85: {=_xlfn.COUNTIFS('외운 것 - 엑셀다운로드 파일(붙여넣기)'!A3:A562,A85,'외운 것 - 엑셀다운로드 파일(붙여넣기)'!D3:D562,0)} -> 5 | L85: {=IF(J85>=3,_xlfn.XLOOKUP(A85,'외운 것 - 엑셀다운로드 파일(붙여넣기)'!A3:A562,'외운 것 - 엑셀다운로드 파일(붙여넣기)'!C3:C562,0,-1),0)} -> 0
A86: 85 | B86: breakthrough | C86: br > break | D86: br | E86: [breiˈkθruˌ] | F86: 문제를 부수고(break) 통과(through)하니, ‘(문제 해결의) 돌파구’ | G86: (문제 해결의) 돌파구 | H86: Scientists announced a breakthrough in cancer research. | I86: {=SUBSTITUTE(H86,B86,"( )")} -> Scientists announced a ( ) in cancer research. | J86: {=SUMIF('외운 것 - 엑셀다운로드 파일(붙여넣기)'!A3:A562,A86,'외운 것 - 엑셀다운로드 파일(붙여넣기)'!D3:D562)} -> 3 | K86: {=_xlfn.COUNTIFS('외운 것 - 엑셀다운로드 파일(붙여넣기)'!A3:A562,A86,'외운 것 - 엑셀다운로드 파일(붙여넣기)'!D3:D562,0)} -> 0 | L86: {=IF(J86>=3,_xlfn.XLOOKUP(A86,'외운 것 - 엑셀다운로드 파일(붙여넣기)'!A3:A562,'외운 것 - 엑셀다운로드 파일(붙여넣기)'!C3:C562,0,-1),0)} -> 2026-03-14
A87: 86 | B87: broker | C87: br > break | D87: br | E87: [bróukər] | F87: 와인 통을 따서(break) 거래를 시작하는 ‘중매인, 중개인’ | G87: 중매인, 중개인 | H87: We hired a real estate broker to help sell our house. | I87: {=SUBSTITUTE(H87,B87,"( )")} -> We hired a real estate ( ) to help sell our house. | J87: {=SUMIF('외운 것 - 엑셀다운로드 파일(붙여넣기)'!A3:A562,A87,'외운 것 - 엑셀다운로드 파일(붙여넣기)'!D3:D562)} -> 3 | K87: {=_xlfn.COUNTIFS('외운 것 - 엑셀다운로드 파일(붙여넣기)'!A3:A562,A87,'외운 것 - 엑셀다운로드 파일(붙여넣기)'!D3:D562,0)} -> 1 | L87: {=IF(J87>=3,_xlfn.XLOOKUP(A87,'외운 것 - 엑셀다운로드 파일(붙여넣기)'!A3:A562,'외운 것 - 엑셀다운로드 파일(붙여넣기)'!C3:C562,0,-1),0)} -> 2026-03-16
A88: 87 | B88: broach | C88: br > break > broker | D88: br | E88: [brouʧ] | F88: 통을 깨서(br) 구멍(o)을 내려고 잡는(ch) 기구 이자 중매인(broker)이 와인 통에 구멍을 내고자 쓰는 도구, ‘(통에 구멍내는) 송곳’ | G88: (통에 구멍내는) 송곳 | H88: It's difficult to broach such a sensitive topic. | I88: {=SUBSTITUTE(H88,B88,"( )")} -> It's difficult to ( ) such a sensitive topic. | J88: {=SUMIF('외운 것 - 엑셀다운로드 파일(붙여넣기)'!A3:A562,A88,'외운 것 - 엑셀다운로드 파일(붙여넣기)'!D3:D562)} -> 3 | K88: {=_xlfn.COUNTIFS('외운 것 - 엑셀다운로드 파일(붙여넣기)'!A3:A562,A88,'외운 것 - 엑셀다운로드 파일(붙여넣기)'!D3:D562,0)} -> 1 | L88: {=IF(J88>=3,_xlfn.XLOOKUP(A88,'외운 것 - 엑셀다운로드 파일(붙여넣기)'!A3:A562,'외운 것 - 엑셀다운로드 파일(붙여넣기)'!C3:C562,0,-1),0)} -> 2026-03-16
A89: 88 | B89: breach | C89: br > break > broach | D89: br | E89: [briːʧ] | F89: 구멍을 내는 송곳(broach)으로 입구(e)를 내는 순간 생기는 ‘터진 구멍, 위반, 침해’ | G89: 터진 구멍, 위반, 침해 | H89: Hackers caused a security breach in the system. | I89: {=SUBSTITUTE(H89,B89,"( )")} -> Hackers caused a security ( ) in the system. | J89: {=SUMIF('외운 것 - 엑셀다운로드 파일(붙여넣기)'!A3:A562,A89,'외운 것 - 엑셀다운로드 파일(붙여넣기)'!D3:D562)} -> 3 | K89: {=_xlfn.COUNTIFS('외운 것 - 엑셀다운로드 파일(붙여넣기)'!A3:A562,A89,'외운 것 - 엑셀다운로드 파일(붙여넣기)'!D3:D562,0)} -> 0 | L89: {=IF(J89>=3,_xlfn.XLOOKUP(A89,'외운 것 - 엑셀다운로드 파일(붙여넣기)'!A3:A562,'외운 것 - 엑셀다운로드 파일(붙여넣기)'!C3:C562,0,-1),0)} -> 2026-03-14
A90: 89 | B90: brick | C90: br > break | D90: br | E90: [brik] | F90: 깨지는(break) 성질이 있어 잘 잡아야(c) 하는 ‘벽돌’ | G90: 벽돌 | H90: They built a brick wall around their garden. | I90: {=SUBSTITUTE(H90,B90,"( )")} -> They built a ( ) wall around their garden. | J90: {=SUMIF('외운 것 - 엑셀다운로드 파일(붙여넣기)'!A3:A562,A90,'외운 것 - 엑셀다운로드 파일(붙여넣기)'!D3:D562)} -> 3 | K90: {=_xlfn.COUNTIFS('외운 것 - 엑셀다운로드 파일(붙여넣기)'!A3:A562,A90,'외운 것 - 엑셀다운로드 파일(붙여넣기)'!D3:D562,0)} -> 0 | L90: {=IF(J90>=3,_xlfn.XLOOKUP(A90,'외운 것 - 엑셀다운로드 파일(붙여넣기)'!A3:A562,'외운 것 - 엑셀다운로드 파일(붙여넣기)'!C3:C562,0,-1),0)} -> 2026-03-14
A91: 90 | B91: brisk | C91: br > break | D91: br | E91: [brisk] | F91: 기운이 터져 나와(br) 표면(sk)에 활발한 기운이 보이니, ‘활발한, 기운찬’ | G91: 활발한, 기운찬 | H91: We took a brisk walk in the cool morning air. | I91: {=SUBSTITUTE(H91,B91,"( )")} -> We took a ( ) walk in the cool morning air. | J91: {=SUMIF('외운 것 - 엑셀다운로드 파일(붙여넣기)'!A3:A562,A91,'외운 것 - 엑셀다운로드 파일(붙여넣기)'!D3:D562)} -> 3 | K91: {=_xlfn.COUNTIFS('외운 것 - 엑셀다운로드 파일(붙여넣기)'!A3:A562,A91,'외운 것 - 엑셀다운로드 파일(붙여넣기)'!D3:D562,0)} -> 0 | L91: {=IF(J91>=3,_xlfn.XLOOKUP(A91,'외운 것 - 엑셀다운로드 파일(붙여넣기)'!A3:A562,'외운 것 - 엑셀다운로드 파일(붙여넣기)'!C3:C562,0,-1),0)} -> 2026-03-14
A92: 91 | B92: brittle | C92: br > break | D92: br | E92: [brítl] | F92: 터져나가(br) 작은 조각(little > ittle)이 되기 쉬운, ‘깨지기 쉬운, 부서지기 쉬운’ | G92: 깨지기 쉬운, 부서지기 쉬운 | H92: The old paper was yellow and brittle with age. | I92: {=SUBSTITUTE(H92,B92,"( )")} -> The old paper was yellow and ( ) with age. | J92: {=SUMIF('외운 것 - 엑셀다운로드 파일(붙여넣기)'!A3:A562,A92,'외운 것 - 엑셀다운로드 파일(붙여넣기)'!D3:D562)} -> 3 | K92: {=_xlfn.COUNTIFS('외운 것 - 엑셀다운로드 파일(붙여넣기)'!A3:A562,A92,'외운 것 - 엑셀다운로드 파일(붙여넣기)'!D3:D562,0)} -> 0 | L92: {=IF(J92>=3,_xlfn.XLOOKUP(A92,'외운 것 - 엑셀다운로드 파일(붙여넣기)'!A3:A562,'외운 것 - 엑셀다운로드 파일(붙여넣기)'!C3:C562,0,-1),0)} -> 2026-03-14
A93: 92 | B93: briquette | C93: br > break | D93: br | E93: [brikét] | F93: 부서져서 터져 나온(br) 가루에 압력(qu)을 가해서 세워(tt) 놓은 것, ‘연탄, 조개탄’ | G93: 연탄, 조개탄 | H93: We need more briquette for the barbecue. | I93: {=SUBSTITUTE(H93,B93,"( )")} -> We need more ( ) for the barbecue. | J93: {=SUMIF('외운 것 - 엑셀다운로드 파일(붙여넣기)'!A3:A562,A93,'외운 것 - 엑셀다운로드 파일(붙여넣기)'!D3:D562)} -> 3 | K93: {=_xlfn.COUNTIFS('외운 것 - 엑셀다운로드 파일(붙여넣기)'!A3:A562,A93,'외운 것 - 엑셀다운로드 파일(붙여넣기)'!D3:D562,0)} -> 0 | L93: {=IF(J93>=3,_xlfn.XLOOKUP(A93,'외운 것 - 엑셀다운로드 파일(붙여넣기)'!A3:A562,'외운 것 - 엑셀다운로드 파일(붙여넣기)'!C3:C562,0,-1),0)} -> 2026-03-14
A94: 93 | B94: broad | C94: br | D94: br | E94: [brɔːd] | F94: 터져서(br) 넓게 길(road)을 만드니 ‘넓은’ | G94: 넓은 | H94: The report covers a broad range of topics. | I94: {=SUBSTITUTE(H94,B94,"( )")} -> The report covers a ( ) range of topics. | J94: {=SUMIF('외운 것 - 엑셀다운로드 파일(붙여넣기)'!A3:A562,A94,'외운 것 - 엑셀다운로드 파일(붙여넣기)'!D3:D562)} -> 3 | K94: {=_xlfn.COUNTIFS('외운 것 - 엑셀다운로드 파일(붙여넣기)'!A3:A562,A94,'외운 것 - 엑셀다운로드 파일(붙여넣기)'!D3:D562,0)} -> 2 | L94: {=IF(J94>=3,_xlfn.XLOOKUP(A94,'외운 것 - 엑셀다운로드 파일(붙여넣기)'!A3:A562,'외운 것 - 엑셀다운로드 파일(붙여넣기)'!C3:C562,0,-1),0)} -> 2026-03-17
A95: 94 | B95: board | C95: br > broad | D95: br | E95: [bɔːrd] | F95: 나무를 넓게(broad) 만든 것이 ‘널판지, 판자’ | G95: 널판지, 판자 | H95: The executive board meets every Tuesday morning. | I95: {=SUBSTITUTE(H95,B95,"( )")} -> The executive ( ) meets every Tuesday morning. | J95: {=SUMIF('외운 것 - 엑셀다운로드 파일(붙여넣기)'!A3:A562,A95,'외운 것 - 엑셀다운로드 파일(붙여넣기)'!D3:D562)} -> 3 | K95: {=_xlfn.COUNTIFS('외운 것 - 엑셀다운로드 파일(붙여넣기)'!A3:A562,A95,'외운 것 - 엑셀다운로드 파일(붙여넣기)'!D3:D562,0)} -> 0 | L95: {=IF(J95>=3,_xlfn.XLOOKUP(A95,'외운 것 - 엑셀다운로드 파일(붙여넣기)'!A3:A562,'외운 것 - 엑셀다운로드 파일(붙여넣기)'!C3:C562,0,-1),0)} -> 2026-03-14
A96: 95 | B96: aboard | C96: br > broad > board | D96: br | E96: [əbɔ́ːrd] | F96: 내 발에 더하는(a) 것이 물 위에 판자(board)이므로 ‘승선하여, (배, 비행기 등을) 타고’ | G96: 승선하여, (배, 비행기 등을) 타고 | H96: All passengers must be aboard the ship by 5:00 PM. | I96: {=SUBSTITUTE(H96,B96,"( )")} -> All passengers must be ( ) the ship by 5:00 PM. | J96: {=SUMIF('외운 것 - 엑셀다운로드 파일(붙여넣기)'!A3:A562,A96,'외운 것 - 엑셀다운로드 파일(붙여넣기)'!D3:D562)} -> 3 | K96: {=_xlfn.COUNTIFS('외운 것 - 엑셀다운로드 파일(붙여넣기)'!A3:A562,A96,'외운 것 - 엑셀다운로드 파일(붙여넣기)'!D3:D562,0)} -> 0 | L96: {=IF(J96>=3,_xlfn.XLOOKUP(A96,'외운 것 - 엑셀다운로드 파일(붙여넣기)'!A3:A562,'외운 것 - 엑셀다운로드 파일(붙여넣기)'!C3:C562,0,-1),0)} -> 2026-03-14
A97: 96 | B97: breadth | C97: br > broad | D97: br | E97: [bredθ, bretθ] | F97: 넓은(broad) 것을 나타내는 ‘너비, 폭, 폭넓음’ | G97: 너비, 폭, 폭넓음 | H97: The breadth of his knowledge on history is impressive. | I97: {=SUBSTITUTE(H97,B97,"( )")} -> The ( ) of his knowledge on history is impressive. | J97: {=SUMIF('외운 것 - 엑셀다운로드 파일(붙여넣기)'!A3:A562,A97,'외운 것 - 엑셀다운로드 파일(붙여넣기)'!D3:D562)} -> 3 | K97: {=_xlfn.COUNTIFS('외운 것 - 엑셀다운로드 파일(붙여넣기)'!A3:A562,A97,'외운 것 - 엑셀다운로드 파일(붙여넣기)'!D3:D562,0)} -> 2 | L97: {=IF(J97>=3,_xlfn.XLOOKUP(A97,'외운 것 - 엑셀다운로드 파일(붙여넣기)'!A3:A562,'외운 것 - 엑셀다운로드 파일(붙여넣기)'!C3:C562,0,-1),0)} -> 2026-03-17
A98: 97 | B98: breath | C98: br | D98: br | E98: [breθ] | F98: 공기가 터져(br) 입과 코를 통과해(th) 나아가는 것, ‘호흡’ | G98: 호흡 | H98: Hold your breath when you swim underwater. | I98: {=SUBSTITUTE(H98,B98,"( )")} -> Hold your ( ) when you swim underwater. | J98: {=SUMIF('외운 것 - 엑셀다운로드 파일(붙여넣기)'!A3:A562,A98,'외운 것 - 엑셀다운로드 파일(붙여넣기)'!D3:D562)} -> 3 | K98: {=_xlfn.COUNTIFS('외운 것 - 엑셀다운로드 파일(붙여넣기)'!A3:A562,A98,'외운 것 - 엑셀다운로드 파일(붙여넣기)'!D3:D562,0)} -> 0 | L98: {=IF(J98>=3,_xlfn.XLOOKUP(A98,'외운 것 - 엑셀다운로드 파일(붙여넣기)'!A3:A562,'외운 것 - 엑셀다운로드 파일(붙여넣기)'!C3:C562,0,-1),0)} -> 2026-03-14
A99: 98 | B99: boil | C99: b | D99: b | E99: [bɔil] | F99: 기포가 터져(b) 나가게 하고 기름(oil)을 이용하기도 하는 동작인 ‘끓이다’ | G99: 끓이다 | H99: You need to boil the water before drinking it. | I99: {=SUBSTITUTE(H99,B99,"( )")} -> You need to ( ) the water before drinking it. | J99: {=SUMIF('외운 것 - 엑셀다운로드 파일(붙여넣기)'!A3:A562,A99,'외운 것 - 엑셀다운로드 파일(붙여넣기)'!D3:D562)} -> 3 | K99: {=_xlfn.COUNTIFS('외운 것 - 엑셀다운로드 파일(붙여넣기)'!A3:A562,A99,'외운 것 - 엑셀다운로드 파일(붙여넣기)'!D3:D562,0)} -> 0 | L99: {=IF(J99>=3,_xlfn.XLOOKUP(A99,'외운 것 - 엑셀다운로드 파일(붙여넣기)'!A3:A562,'외운 것 - 엑셀다운로드 파일(붙여넣기)'!C3:C562,0,-1),0)} -> 2026-03-14
A100: 99 | B100: broil | C100: br | D100: br | E100: [brɔil] | F100: 고기 등이 익어서 터질(br)듯이 기름(oil)으로 지글지글 ‘굽다’ | G100: 굽다 | H100: Set the oven to broil when cooking the fish. | I100: {=SUBSTITUTE(H100,B100,"( )")} -> Set the oven to ( ) when cooking the fish. | J100: {=SUMIF('외운 것 - 엑셀다운로드 파일(붙여넣기)'!A3:A562,A100,'외운 것 - 엑셀다운로드 파일(붙여넣기)'!D3:D562)} -> 3 | K100: {=_xlfn.COUNTIFS('외운 것 - 엑셀다운로드 파일(붙여넣기)'!A3:A562,A100,'외운 것 - 엑셀다운로드 파일(붙여넣기)'!D3:D562,0)} -> 0 | L100: {=IF(J100>=3,_xlfn.XLOOKUP(A100,'외운 것 - 엑셀다운로드 파일(붙여넣기)'!A3:A562,'외운 것 - 엑셀다운로드 파일(붙여넣기)'!C3:C562,0,-1),0)} -> 2026-03-14
...

Sheet 외운 것 - 엑셀다운로드 파일(붙여넣기)
A2: No2 | B2: 영어단어2 | C2: 날짜2 | D2: 외운것2 | E2: 비고(numbers) | F2: 순서
A3: 1655 | B3: population | C3: 2026-03-15 | D3: 1 | E3: {=_xlfn.COUNTIFS(B3:B562,B3,D3:D562,1,A3:A562,A3)} -> 1 | F3: {=(YEAR(C3)-2025)*1000+MONTH(C3)*31+DAY(C3)+A3} -> 2763
A4: 1654 | B4: popularity | C4: 2026-03-15 | D4: 1 | E4: {=_xlfn.COUNTIFS(B3:B562,B4,D3:D562,1,A3:A562,A4)} -> 1 | F4: {=(YEAR(C4)-2025)*1000+MONTH(C4)*31+DAY(C4)+A4} -> 2762
A5: 1653 | B5: popular | C5: 2026-03-15 | D5: 3 | E5: {=_xlfn.COUNTIFS(B3:B562,B5,D3:D562,1,A3:A562,A5)} -> 0 | F5: {=(YEAR(C5)-2025)*1000+MONTH(C5)*31+DAY(C5)+A5} -> 2761
A6: 1652 | B6: popsong | C6: 2026-03-15 | D6: 3 | E6: {=_xlfn.COUNTIFS(B3:B562,B6,D3:D562,1,A3:A562,A6)} -> 0 | F6: {=(YEAR(C6)-2025)*1000+MONTH(C6)*31+DAY(C6)+A6} -> 2760
A7: 1651 | B7: popcorn | C7: 2026-03-15 | D7: 3 | E7: {=_xlfn.COUNTIFS(B3:B562,B7,D3:D562,1,A3:A562,A7)} -> 0 | F7: {=(YEAR(C7)-2025)*1000+MONTH(C7)*31+DAY(C7)+A7} -> 2759
A8: 1650 | B8: surplus | C8: 2026-03-15 | D8: 0 | E8: {=_xlfn.COUNTIFS(B3:B562,B8,D3:D562,1,A3:A562,A8)} -> 0 | F8: {=(YEAR(C8)-2025)*1000+MONTH(C8)*31+DAY(C8)+A8} -> 2758
A9: 1649 | B9: plus | C9: 2026-03-15 | D9: 3 | E9: {=_xlfn.COUNTIFS(B3:B562,B9,D3:D562,1,A3:A562,A9)} -> 0 | F9: {=(YEAR(C9)-2025)*1000+MONTH(C9)*31+DAY(C9)+A9} -> 2757
A10: 1648 | B10: monopoly | C10: 2026-03-15 | D10: 1 | E10: {=_xlfn.COUNTIFS(B3:B562,B10,D3:D562,1,A3:A562,A10)} -> 1 | F10: {=(YEAR(C10)-2025)*1000+MONTH(C10)*31+DAY(C10)+A10} -> 2756
A11: 1647 | B11: employee | C11: 2026-03-15 | D11: 1 | E11: {=_xlfn.COUNTIFS(B3:B562,B11,D3:D562,1,A3:A562,A11)} -> 1 | F11: {=(YEAR(C11)-2025)*1000+MONTH(C11)*31+DAY(C11)+A11} -> 2755
A12: 1646 | B12: employer | C12: 2026-03-15 | D12: 1 | E12: {=_xlfn.COUNTIFS(B3:B562,B12,D3:D562,1,A3:A562,A12)} -> 1 | F12: {=(YEAR(C12)-2025)*1000+MONTH(C12)*31+DAY(C12)+A12} -> 2754
A13: 1645 | B13: employ | C13: 2026-03-15 | D13: 0 | E13: {=_xlfn.COUNTIFS(B3:B562,B13,D3:D562,1,A3:A562,A13)} -> 0 | F13: {=(YEAR(C13)-2025)*1000+MONTH(C13)*31+DAY(C13)+A13} -> 2753
A14: 1644 | B14: applicant | C14: 2026-03-15 | D14: 1 | E14: {=_xlfn.COUNTIFS(B3:B562,B14,D3:D562,1,A3:A562,A14)} -> 1 | F14: {=(YEAR(C14)-2025)*1000+MONTH(C14)*31+DAY(C14)+A14} -> 2752
A15: 1643 | B15: apply | C15: 2026-03-15 | D15: 1 | E15: {=_xlfn.COUNTIFS(B3:B562,B15,D3:D562,1,A3:A562,A15)} -> 1 | F15: {=(YEAR(C15)-2025)*1000+MONTH(C15)*31+DAY(C15)+A15} -> 2751
A16: 1642 | B16: reply | C16: 2026-03-15 | D16: 1 | E16: {=_xlfn.COUNTIFS(B3:B562,B16,D3:D562,1,A3:A562,A16)} -> 1 | F16: {=(YEAR(C16)-2025)*1000+MONTH(C16)*31+DAY(C16)+A16} -> 2750
A17: 1641 | B17: comply | C17: 2026-03-15 | D17: 1 | E17: {=_xlfn.COUNTIFS(B3:B562,B17,D3:D562,1,A3:A562,A17)} -> 1 | F17: {=(YEAR(C17)-2025)*1000+MONTH(C17)*31+DAY(C17)+A17} -> 2749
A18: 1640 | B18: accomplish | C18: 2026-03-15 | D18: 0 | E18: {=_xlfn.COUNTIFS(B3:B562,B18,D3:D562,1,A3:A562,A18)} -> 0 | F18: {=(YEAR(C18)-2025)*1000+MONTH(C18)*31+DAY(C18)+A18} -> 2748
A19: 1639 | B19: duplicate | C19: 2026-03-15 | D19: 0 | E19: {=_xlfn.COUNTIFS(B3:B562,B19,D3:D562,1,A3:A562,A19)} -> 0 | F19: {=(YEAR(C19)-2025)*1000+MONTH(C19)*31+DAY(C19)+A19} -> 2747
A20: 1638 | B20: implicate | C20: 2026-03-15 | D20: 0 | E20: {=_xlfn.COUNTIFS(B3:B562,B20,D3:D562,1,A3:A562,A20)} -> 0 | F20: {=(YEAR(C20)-2025)*1000+MONTH(C20)*31+DAY(C20)+A20} -> 2746
A21: 1637 | B21: complicate | C21: 2026-03-15 | D21: 1 | E21: {=_xlfn.COUNTIFS(B3:B562,B21,D3:D562,1,A3:A562,A21)} -> 1 | F21: {=(YEAR(C21)-2025)*1000+MONTH(C21)*31+DAY(C21)+A21} -> 2745
A22: 1636 | B22: complex | C22: 2026-03-15 | D22: 1 | E22: {=_xlfn.COUNTIFS(B3:B562,B22,D3:D562,1,A3:A562,A22)} -> 1 | F22: {=(YEAR(C22)-2025)*1000+MONTH(C22)*31+DAY(C22)+A22} -> 2744
A23: 1635 | B23: implement | C23: 2026-03-15 | D23: 0 | E23: {=_xlfn.COUNTIFS(B3:B562,B23,D3:D562,1,A3:A562,A23)} -> 0 | F23: {=(YEAR(C23)-2025)*1000+MONTH(C23)*31+DAY(C23)+A23} -> 2743
A24: 1634 | B24: supplement | C24: 2026-03-15 | D24: 0 | E24: {=_xlfn.COUNTIFS(B3:B562,B24,D3:D562,1,A3:A562,A24)} -> 0 | F24: {=(YEAR(C24)-2025)*1000+MONTH(C24)*31+DAY(C24)+A24} -> 2742
A25: 1633 | B25: compliment | C25: 2026-03-15 | D25: 0 | E25: {=_xlfn.COUNTIFS(B3:B562,B25,D3:D562,1,A3:A562,A25)} -> 0 | F25: {=(YEAR(C25)-2025)*1000+MONTH(C25)*31+DAY(C25)+A25} -> 2741
A26: 1632 | B26: complement | C26: 2026-03-15 | D26: 0 | E26: {=_xlfn.COUNTIFS(B3:B562,B26,D3:D562,1,A3:A562,A26)} -> 0 | F26: {=(YEAR(C26)-2025)*1000+MONTH(C26)*31+DAY(C26)+A26} -> 2740
A27: 1631 | B27: incomplete | C27: 2026-03-15 | D27: 1 | E27: {=_xlfn.COUNTIFS(B3:B562,B27,D3:D562,1,A3:A562,A27)} -> 1 | F27: {=(YEAR(C27)-2025)*1000+MONTH(C27)*31+DAY(C27)+A27} -> 2739
A28: 1630 | B28: complete | C28: 2026-03-15 | D28: 1 | E28: {=_xlfn.COUNTIFS(B3:B562,B28,D3:D562,1,A3:A562,A28)} -> 1 | F28: {=(YEAR(C28)-2025)*1000+MONTH(C28)*31+DAY(C28)+A28} -> 2738
A29: 1629 | B29: deplete | C29: 2026-03-15 | D29: 1 | E29: {=_xlfn.COUNTIFS(B3:B562,B29,D3:D562,1,A3:A562,A29)} -> 1 | F29: {=(YEAR(C29)-2025)*1000+MONTH(C29)*31+DAY(C29)+A29} -> 2737
A30: 1628 | B30: multiply | C30: 2026-03-15 | D30: 0 | E30: {=_xlfn.COUNTIFS(B3:B562,B30,D3:D562,1,A3:A562,A30)} -> 0 | F30: {=(YEAR(C30)-2025)*1000+MONTH(C30)*31+DAY(C30)+A30} -> 2736
A31: 1627 | B31: multiple | C31: 2026-03-15 | D31: 1 | E31: {=_xlfn.COUNTIFS(B3:B562,B31,D3:D562,1,A3:A562,A31)} -> 1 | F31: {=(YEAR(C31)-2025)*1000+MONTH(C31)*31+DAY(C31)+A31} -> 2735
A32: 1626 | B32: plenty | C32: 2026-03-15 | D32: 1 | E32: {=_xlfn.COUNTIFS(B3:B562,B32,D3:D562,1,A3:A562,A32)} -> 1 | F32: {=(YEAR(C32)-2025)*1000+MONTH(C32)*31+DAY(C32)+A32} -> 2734
A33: 1625 | B33: supplant | C33: 2026-03-15 | D33: 0 | E33: {=_xlfn.COUNTIFS(B3:B562,B33,D3:D562,1,A3:A562,A33)} -> 0 | F33: {=(YEAR(C33)-2025)*1000+MONTH(C33)*31+DAY(C33)+A33} -> 2733
A34: 1624 | B34: implant | C34: 2026-03-15 | D34: 1 | E34: {=_xlfn.COUNTIFS(B3:B562,B34,D3:D562,1,A3:A562,A34)} -> 1 | F34: {=(YEAR(C34)-2025)*1000+MONTH(C34)*31+DAY(C34)+A34} -> 2732
A35: 1623 | B35: plant | C35: 2026-03-15 | D35: 1 | E35: {=_xlfn.COUNTIFS(B3:B562,B35,D3:D562,1,A3:A562,A35)} -> 1 | F35: {=(YEAR(C35)-2025)*1000+MONTH(C35)*31+DAY(C35)+A35} -> 2731
A36: 1622 | B36: complain | C36: 2026-03-15 | D36: 1 | E36: {=_xlfn.COUNTIFS(B3:B562,B36,D3:D562,1,A3:A562,A36)} -> 1 | F36: {=(YEAR(C36)-2025)*1000+MONTH(C36)*31+DAY(C36)+A36} -> 2730
A37: 1621 | B37: explain | C37: 2026-03-15 | D37: 1 | E37: {=_xlfn.COUNTIFS(B3:B562,B37,D3:D562,1,A3:A562,A37)} -> 1 | F37: {=(YEAR(C37)-2025)*1000+MONTH(C37)*31+DAY(C37)+A37} -> 2729
A38: 1620 | B38: plain | C38: 2026-03-15 | D38: 1 | E38: {=_xlfn.COUNTIFS(B3:B562,B38,D3:D562,1,A3:A562,A38)} -> 1 | F38: {=(YEAR(C38)-2025)*1000+MONTH(C38)*31+DAY(C38)+A38} -> 2728
A39: 1619 | B39: planet | C39: 2026-03-15 | D39: 1 | E39: {=_xlfn.COUNTIFS(B3:B562,B39,D3:D562,1,A3:A562,A39)} -> 1 | F39: {=(YEAR(C39)-2025)*1000+MONTH(C39)*31+DAY(C39)+A39} -> 2727
A40: 1618 | B40: airplane | C40: 2026-03-15 | D40: 1 | E40: {=_xlfn.COUNTIFS(B3:B562,B40,D3:D562,1,A3:A562,A40)} -> 1 | F40: {=(YEAR(C40)-2025)*1000+MONTH(C40)*31+DAY(C40)+A40} -> 2726
A41: 1617 | B41: plan | C41: 2026-03-15 | D41: 1 | E41: {=_xlfn.COUNTIFS(B3:B562,B41,D3:D562,1,A3:A562,A41)} -> 1 | F41: {=(YEAR(C41)-2025)*1000+MONTH(C41)*31+DAY(C41)+A41} -> 2725
A42: 1616 | B42: displace | C42: 2026-03-15 | D42: 0 | E42: {=_xlfn.COUNTIFS(B3:B562,B42,D3:D562,1,A3:A562,A42)} -> 0 | F42: {=(YEAR(C42)-2025)*1000+MONTH(C42)*31+DAY(C42)+A42} -> 2724
A43: 1615 | B43: replace | C43: 2026-03-15 | D43: 1 | E43: {=_xlfn.COUNTIFS(B3:B562,B43,D3:D562,1,A3:A562,A43)} -> 1 | F43: {=(YEAR(C43)-2025)*1000+MONTH(C43)*31+DAY(C43)+A43} -> 2723
A44: 1611 | B44: plaster | C44: 2026-03-15 | D44: 1 | E44: {=_xlfn.COUNTIFS(B3:B562,B44,D3:D562,1,A3:A562,A44)} -> 1 | F44: {=(YEAR(C44)-2025)*1000+MONTH(C44)*31+DAY(C44)+A44} -> 2719
A45: 1609 | B45: plat | C45: 2026-03-15 | D45: 1 | E45: {=_xlfn.COUNTIFS(B3:B562,B45,D3:D562,1,A3:A562,A45)} -> 1 | F45: {=(YEAR(C45)-2025)*1000+MONTH(C45)*31+DAY(C45)+A45} -> 2717
A46: 1608 | B46: plaza | C46: 2026-03-15 | D46: 1 | E46: {=_xlfn.COUNTIFS(B3:B562,B46,D3:D562,1,A3:A562,A46)} -> 1 | F46: {=(YEAR(C46)-2025)*1000+MONTH(C46)*31+DAY(C46)+A46} -> 2716
A47: 1606 | B47: permanent | C47: 2026-03-15 | D47: 0 | E47: {=_xlfn.COUNTIFS(B3:B562,B47,D3:D562,1,A3:A562,A47)} -> 0 | F47: {=(YEAR(C47)-2025)*1000+MONTH(C47)*31+DAY(C47)+A47} -> 2714
A48: 1603 | B48: personnel | C48: 2026-03-15 | D48: 1 | E48: {=_xlfn.COUNTIFS(B3:B562,B48,D3:D562,1,A3:A562,A48)} -> 1 | F48: {=(YEAR(C48)-2025)*1000+MONTH(C48)*31+DAY(C48)+A48} -> 2711
A49: 1601 | B49: fume | C49: 2026-03-15 | D49: 1 | E49: {=_xlfn.COUNTIFS(B3:B562,B49,D3:D562,1,A3:A562,A49)} -> 1 | F49: {=(YEAR(C49)-2025)*1000+MONTH(C49)*31+DAY(C49)+A49} -> 2709
A50: 1597 | B50: compensate | C50: 2026-03-15 | D50: 1 | E50: {=_xlfn.COUNTIFS(B3:B562,B50,D3:D562,1,A3:A562,A50)} -> 1 | F50: {=(YEAR(C50)-2025)*1000+MONTH(C50)*31+DAY(C50)+A50} -> 2705
A51: 1596 | B51: expend | C51: 2026-03-15 | D51: 0 | E51: {=_xlfn.COUNTIFS(B3:B562,B51,D3:D562,1,A3:A562,A51)} -> 0 | F51: {=(YEAR(C51)-2025)*1000+MONTH(C51)*31+DAY(C51)+A51} -> 2704
A52: 1595 | B52: indispensable | C52: 2026-03-15 | D52: 1 | E52: {=_xlfn.COUNTIFS(B3:B562,B52,D3:D562,1,A3:A562,A52)} -> 1 | F52: {=(YEAR(C52)-2025)*1000+MONTH(C52)*31+DAY(C52)+A52} -> 2703
A53: 1594 | B53: dispensable | C53: 2026-03-15 | D53: 0 | E53: {=_xlfn.COUNTIFS(B3:B562,B53,D3:D562,1,A3:A562,A53)} -> 0 | F53: {=(YEAR(C53)-2025)*1000+MONTH(C53)*31+DAY(C53)+A53} -> 2702
A54: 1591 | B54: suspend | C54: 2026-03-15 | D54: 1 | E54: {=_xlfn.COUNTIFS(B3:B562,B54,D3:D562,1,A3:A562,A54)} -> 1 | F54: {=(YEAR(C54)-2025)*1000+MONTH(C54)*31+DAY(C54)+A54} -> 2699
A55: 1587 | B55: pendant | C55: 2026-03-15 | D55: 0 | E55: {=_xlfn.COUNTIFS(B3:B562,B55,D3:D562,1,A3:A562,A55)} -> 0 | F55: {=(YEAR(C55)-2025)*1000+MONTH(C55)*31+DAY(C55)+A55} -> 2695
A56: 1586 | B56: appeal | C56: 2026-03-15 | D56: 1 | E56: {=_xlfn.COUNTIFS(B3:B562,B56,D3:D562,1,A3:A562,A56)} -> 1 | F56: {=(YEAR(C56)-2025)*1000+MONTH(C56)*31+DAY(C56)+A56} -> 2694
A57: 1585 | B57: compulsory | C57: 2026-03-15 | D57: 1 | E57: {=_xlfn.COUNTIFS(B3:B562,B57,D3:D562,1,A3:A562,A57)} -> 1 | F57: {=(YEAR(C57)-2025)*1000+MONTH(C57)*31+DAY(C57)+A57} -> 2693
A58: 1582 | B58: dispel | C58: 2026-03-15 | D58: 1 | E58: {=_xlfn.COUNTIFS(B3:B562,B58,D3:D562,1,A3:A562,A58)} -> 1 | F58: {=(YEAR(C58)-2025)*1000+MONTH(C58)*31+DAY(C58)+A58} -> 2690
A59: 1580 | B59: repel | C59: 2026-03-15 | D59: 0 | E59: {=_xlfn.COUNTIFS(B3:B562,B59,D3:D562,1,A3:A562,A59)} -> 0 | F59: {=(YEAR(C59)-2025)*1000+MONTH(C59)*31+DAY(C59)+A59} -> 2688
A60: 1574 | B60: pathetic | C60: 2026-03-15 | D60: 1 | E60: {=_xlfn.COUNTIFS(B3:B562,B60,D3:D562,1,A3:A562,A60)} -> 1 | F60: {=(YEAR(C60)-2025)*1000+MONTH(C60)*31+DAY(C60)+A60} -> 2682
A61: 1573 | B61: compassion | C61: 2026-03-15 | D61: 1 | E61: {=_xlfn.COUNTIFS(B3:B562,B61,D3:D562,1,A3:A562,A61)} -> 1 | F61: {=(YEAR(C61)-2025)*1000+MONTH(C61)*31+DAY(C61)+A61} -> 2681
A62: 1558 | B62: counterpart | C62: 2026-03-15 | D62: 1 | E62: {=_xlfn.COUNTIFS(B3:B562,B62,D3:D562,1,A3:A562,A62)} -> 1 | F62: {=(YEAR(C62)-2025)*1000+MONTH(C62)*31+DAY(C62)+A62} -> 2666
A63: 185 | B63: carriage | C63: 2026-03-17 | D63: 1 | E63: {=_xlfn.COUNTIFS(B3:B562,B63,D3:D562,1,A3:A562,A63)} -> 1 | F63: {=(YEAR(C63)-2025)*1000+MONTH(C63)*31+DAY(C63)+A63} -> 1295
A64: 184 | B64: carrier | C64: 2026-03-17 | D64: 1 | E64: {=_xlfn.COUNTIFS(B3:B562,B64,D3:D562,1,A3:A562,A64)} -> 1 | F64: {=(YEAR(C64)-2025)*1000+MONTH(C64)*31+DAY(C64)+A64} -> 1294
A65: 183 | B65: carry | C65: 2026-03-17 | D65: 1 | E65: {=_xlfn.COUNTIFS(B3:B562,B65,D3:D562,1,A3:A562,A65)} -> 1 | F65: {=(YEAR(C65)-2025)*1000+MONTH(C65)*31+DAY(C65)+A65} -> 1293
A66: 182 | B66: carton | C66: 2026-03-17 | D66: 1 | E66: {=_xlfn.COUNTIFS(B3:B562,B66,D3:D562,1,A3:A562,A66)} -> 1 | F66: {=(YEAR(C66)-2025)*1000+MONTH(C66)*31+DAY(C66)+A66} -> 1292
A67: 181 | B67: cart | C67: 2026-03-17 | D67: 1 | E67: {=_xlfn.COUNTIFS(B3:B562,B67,D3:D562,1,A3:A562,A67)} -> 1 | F67: {=(YEAR(C67)-2025)*1000+MONTH(C67)*31+DAY(C67)+A67} -> 1291
A68: 180 | B68: carpenter | C68: 2026-03-17 | D68: 0 | E68: {=_xlfn.COUNTIFS(B3:B562,B68,D3:D562,1,A3:A562,A68)} -> 0 | F68: {=(YEAR(C68)-2025)*1000+MONTH(C68)*31+DAY(C68)+A68} -> 1290
A69: 179 | B69: cargo | C69: 2026-03-17 | D69: 1 | E69: {=_xlfn.COUNTIFS(B3:B562,B69,D3:D562,1,A3:A562,A69)} -> 1 | F69: {=(YEAR(C69)-2025)*1000+MONTH(C69)*31+DAY(C69)+A69} -> 1289
A70: 178 | B70: car | C70: 2026-03-17 | D70: 1 | E70: {=_xlfn.COUNTIFS(B3:B562,B70,D3:D562,1,A3:A562,A70)} -> 1 | F70: {=(YEAR(C70)-2025)*1000+MONTH(C70)*31+DAY(C70)+A70} -> 1288
A71: 177 | B71: preoccupied | C71: 2026-03-17 | D71: 1 | E71: {=_xlfn.COUNTIFS(B3:B562,B71,D3:D562,1,A3:A562,A71)} -> 1 | F71: {=(YEAR(C71)-2025)*1000+MONTH(C71)*31+DAY(C71)+A71} -> 1287
A72: 176 | B72: preoccupy | C72: 2026-03-17 | D72: 1 | E72: {=_xlfn.COUNTIFS(B3:B562,B72,D3:D562,1,A3:A562,A72)} -> 1 | F72: {=(YEAR(C72)-2025)*1000+MONTH(C72)*31+DAY(C72)+A72} -> 1286
A73: 175 | B73: occupy | C73: 2026-03-17 | D73: 1 | E73: {=_xlfn.COUNTIFS(B3:B562,B73,D3:D562,1,A3:A562,A73)} -> 1 | F73: {=(YEAR(C73)-2025)*1000+MONTH(C73)*31+DAY(C73)+A73} -> 1285
A74: 174 | B74: participate | C74: 2026-03-17 | D74: 1 | E74: {=_xlfn.COUNTIFS(B3:B562,B74,D3:D562,1,A3:A562,A74)} -> 1 | F74: {=(YEAR(C74)-2025)*1000+MONTH(C74)*31+DAY(C74)+A74} -> 1284
A75: 173 | B75: principle | C75: 2026-03-17 | D75: 1 | E75: {=_xlfn.COUNTIFS(B3:B562,B75,D3:D562,1,A3:A562,A75)} -> 1 | F75: {=(YEAR(C75)-2025)*1000+MONTH(C75)*31+DAY(C75)+A75} -> 1283
A76: 172 | B76: reciprocal | C76: 2026-03-17 | D76: 0 | E76: {=_xlfn.COUNTIFS(B3:B562,B76,D3:D562,1,A3:A562,A76)} -> 0 | F76: {=(YEAR(C76)-2025)*1000+MONTH(C76)*31+DAY(C76)+A76} -> 1282
A77: 171 | B77: principal | C77: 2026-03-17 | D77: 0 | E77: {=_xlfn.COUNTIFS(B3:B562,B77,D3:D562,1,A3:A562,A77)} -> 0 | F77: {=(YEAR(C77)-2025)*1000+MONTH(C77)*31+DAY(C77)+A77} -> 1281
A78: 171 | B78: principal | C78: 2026-03-16 | D78: 0 | E78: {=_xlfn.COUNTIFS(B3:B562,B78,D3:D562,1,A3:A562,A78)} -> 0 | F78: {=(YEAR(C78)-2025)*1000+MONTH(C78)*31+DAY(C78)+A78} -> 1280
A79: 170 | B79: precipitate | C79: 2026-03-17 | D79: 0 | E79: {=_xlfn.COUNTIFS(B3:B562,B79,D3:D562,1,A3:A562,A79)} -> 0 | F79: {=(YEAR(C79)-2025)*1000+MONTH(C79)*31+DAY(C79)+A79} -> 1280
A80: 170 | B80: precipitate | C80: 2026-03-16 | D80: 0 | E80: {=_xlfn.COUNTIFS(B3:B562,B80,D3:D562,1,A3:A562,A80)} -> 0 | F80: {=(YEAR(C80)-2025)*1000+MONTH(C80)*31+DAY(C80)+A80} -> 1279
A81: 169 | B81: discipline | C81: 2026-03-17 | D81: 0 | E81: {=_xlfn.COUNTIFS(B3:B562,B81,D3:D562,1,A3:A562,A81)} -> 0 | F81: {=(YEAR(C81)-2025)*1000+MONTH(C81)*31+DAY(C81)+A81} -> 1279
A82: 169 | B82: discipline | C82: 2026-03-16 | D82: 0 | E82: {=_xlfn.COUNTIFS(B3:B562,B82,D3:D562,1,A3:A562,A82)} -> 0 | F82: {=(YEAR(C82)-2025)*1000+MONTH(C82)*31+DAY(C82)+A82} -> 1278
A83: 168 | B83: disciple | C83: 2026-03-17 | D83: 1 | E83: {=_xlfn.COUNTIFS(B3:B562,B83,D3:D562,1,A3:A562,A83)} -> 2 | F83: {=(YEAR(C83)-2025)*1000+MONTH(C83)*31+DAY(C83)+A83} -> 1278
A84: 168 | B84: disciple | C84: 2026-03-16 | D84: 1 | E84: {=_xlfn.COUNTIFS(B3:B562,B84,D3:D562,1,A3:A562,A84)} -> 2 | F84: {=(YEAR(C84)-2025)*1000+MONTH(C84)*31+DAY(C84)+A84} -> 1277
A85: 167 | B85: anticipate | C85: 2026-03-17 | D85: 1 | E85: {=_xlfn.COUNTIFS(B3:B562,B85,D3:D562,1,A3:A562,A85)} -> 2 | F85: {=(YEAR(C85)-2025)*1000+MONTH(C85)*31+DAY(C85)+A85} -> 1277
A86: 167 | B86: anticipate | C86: 2026-03-16 | D86: 1 | E86: {=_xlfn.COUNTIFS(B3:B562,B86,D3:D562,1,A3:A562,A86)} -> 2 | F86: {=(YEAR(C86)-2025)*1000+MONTH(C86)*31+DAY(C86)+A86} -> 1276
A87: 166 | B87: recipe | C87: 2026-03-17 | D87: 0 | E87: {=_xlfn.COUNTIFS(B3:B562,B87,D3:D562,1,A3:A562,A87)} -> 0 | F87: {=(YEAR(C87)-2025)*1000+MONTH(C87)*31+DAY(C87)+A87} -> 1276
A88: 166 | B88: recipe | C88: 2026-03-16 | D88: 0 | E88: {=_xlfn.COUNTIFS(B3:B562,B88,D3:D562,1,A3:A562,A88)} -> 0 | F88: {=(YEAR(C88)-2025)*1000+MONTH(C88)*31+DAY(C88)+A88} -> 1275
A89: 165 | B89: intercept | C89: 2026-03-17 | D89: 1 | E89: {=_xlfn.COUNTIFS(B3:B562,B89,D3:D562,1,A3:A562,A89)} -> 2 | F89: {=(YEAR(C89)-2025)*1000+MONTH(C89)*31+DAY(C89)+A89} -> 1275
A90: 165 | B90: intercept | C90: 2026-03-16 | D90: 1 | E90: {=_xlfn.COUNTIFS(B3:B562,B90,D3:D562,1,A3:A562,A90)} -> 2 | F90: {=(YEAR(C90)-2025)*1000+MONTH(C90)*31+DAY(C90)+A90} -> 1274
A91: 164 | B91: deception | C91: 2026-03-17 | D91: 0 | E91: {=_xlfn.COUNTIFS(B3:B562,B91,D3:D562,1,A3:A562,A91)} -> 0 | F91: {=(YEAR(C91)-2025)*1000+MONTH(C91)*31+DAY(C91)+A91} -> 1274
A92: 164 | B92: deception | C92: 2026-03-16 | D92: 0 | E92: {=_xlfn.COUNTIFS(B3:B562,B92,D3:D562,1,A3:A562,A92)} -> 0 | F92: {=(YEAR(C92)-2025)*1000+MONTH(C92)*31+DAY(C92)+A92} -> 1273
A93: 163 | B93: excerpt | C93: 2026-03-17 | D93: 0 | E93: {=_xlfn.COUNTIFS(B3:B562,B93,D3:D562,1,A3:A562,A93)} -> 0 | F93: {=(YEAR(C93)-2025)*1000+MONTH(C93)*31+DAY(C93)+A93} -> 1273
A94: 163 | B94: excerpt | C94: 2026-03-16 | D94: 0 | E94: {=_xlfn.COUNTIFS(B3:B562,B94,D3:D562,1,A3:A562,A94)} -> 0 | F94: {=(YEAR(C94)-2025)*1000+MONTH(C94)*31+DAY(C94)+A94} -> 1272
A95: 162 | B95: exceptional | C95: 2026-03-17 | D95: 1 | E95: {=_xlfn.COUNTIFS(B3:B562,B95,D3:D562,1,A3:A562,A95)} -> 2 | F95: {=(YEAR(C95)-2025)*1000+MONTH(C95)*31+DAY(C95)+A95} -> 1272
A96: 162 | B96: exceptional | C96: 2026-03-16 | D96: 1 | E96: {=_xlfn.COUNTIFS(B3:B562,B96,D3:D562,1,A3:A562,A96)} -> 2 | F96: {=(YEAR(C96)-2025)*1000+MONTH(C96)*31+DAY(C96)+A96} -> 1271
A97: 161 | B97: exception | C97: 2026-03-17 | D97: 1 | E97: {=_xlfn.COUNTIFS(B3:B562,B97,D3:D562,1,A3:A562,A97)} -> 2 | F97: {=(YEAR(C97)-2025)*1000+MONTH(C97)*31+DAY(C97)+A97} -> 1271
A98: 161 | B98: exception | C98: 2026-03-16 | D98: 1 | E98: {=_xlfn.COUNTIFS(B3:B562,B98,D3:D562,1,A3:A562,A98)} -> 2 | F98: {=(YEAR(C98)-2025)*1000+MONTH(C98)*31+DAY(C98)+A98} -> 1270
A99: 160 | B99: except | C99: 2026-03-17 | D99: 1 | E99: {=_xlfn.COUNTIFS(B3:B562,B99,D3:D562,1,A3:A562,A99)} -> 2 | F99: {=(YEAR(C99)-2025)*1000+MONTH(C99)*31+DAY(C99)+A99} -> 1270
A100: 160 | B100: except | C100: 2026-03-16 | D100: 1 | E100: {=_xlfn.COUNTIFS(B3:B562,B100,D3:D562,1,A3:A562,A100)} -> 2 | F100: {=(YEAR(C100)-2025)*1000+MONTH(C100)*31+DAY(C100)+A100} -> 1269
A101: 159 | B101: receipt | C101: 2026-03-17 | D101: 1 | E101: {=_xlfn.COUNTIFS(B3:B562,B101,D3:D562,1,A3:A562,A101)} -> 2 | F101: {=(YEAR(C101)-2025)*1000+MONTH(C101)*31+DAY(C101)+A101} -> 1269
...

Sheet 총괄 - 틀린 것
A1: 틀린 것
A2: 틀린것 | B2: 영어단어 | C2: 외운것 | D2: No(전체 항목 세기)
A3: 1 | D3: 22

Sheet 총괄 - 전체
A1: 전체
A2: 외운 갯수 | B2: 남은 갯수
A3: {=COUNTIF('어휘 - 표 1 스냅샷'!J2:J2503,">=3")} -> 96 | B3: {=COUNTA('어휘 - 표 1 스냅샷'!A2:A2503)-A3} -> 2406

Sheet 총괄 - 3번 맞춘단어
A1: 3번 맞춘단어
B2: 날짜 | C2: 맞춘갯수(순서 체크) | D2: 회차
A3: 날짜: | C3: 합계:
A4: 46082 | C4: =SUM(C5:C23) -> 96
B5: 46094 | C5: {=COUNTIF('어휘 - 표 1 스냅샷'!L2:L2503,B5)} -> 0 | D5: {=COUNTIF('외운 것 - 엑셀다운로드 파일(붙여넣기)'!C3:C562,B5)/100} -> 1
B6: 46095 | C6: {=COUNTIF('어휘 - 표 1 스냅샷'!L2:L2503,B6)} -> 71 | D6: {=COUNTIF('외운 것 - 엑셀다운로드 파일(붙여넣기)'!C3:C562,B6)/100} -> 2
B7: 46096 | C7: {=COUNTIF('어휘 - 표 1 스냅샷'!L2:L2503,B7)} -> 4 | D7: {=COUNTIF('외운 것 - 엑셀다운로드 파일(붙여넣기)'!C3:C562,B7)/100} -> 0.6
B8: 46097 | C8: {=COUNTIF('어휘 - 표 1 스냅샷'!L2:L2503,B8)} -> 14 | D8: {=COUNTIF('외운 것 - 엑셀다운로드 파일(붙여넣기)'!C3:C562,B8)/100} -> 1
B9: 46098 | C9: {=COUNTIF('어휘 - 표 1 스냅샷'!L2:L2503,B9)} -> 7 | D9: {=COUNTIF('외운 것 - 엑셀다운로드 파일(붙여넣기)'!C3:C562,B9)/100} -> 1
B10: 46099 | C10: {=COUNTIF('어휘 - 표 1 스냅샷'!L2:L2503,B10)} -> 0 | D10: {=COUNTIF('외운 것 - 엑셀다운로드 파일(붙여넣기)'!C3:C562,B10)/100} -> 0
B11: 46100 | C11: {=COUNTIF('어휘 - 표 1 스냅샷'!L2:L2503,B11)} -> 0 | D11: {=COUNTIF('외운 것 - 엑셀다운로드 파일(붙여넣기)'!C3:C562,B11)/100} -> 0
B12: 46101 | C12: {=COUNTIF('어휘 - 표 1 스냅샷'!L2:L2503,B12)} -> 0 | D12: {=COUNTIF('외운 것 - 엑셀다운로드 파일(붙여넣기)'!C3:C562,B12)/100} -> 0
B13: 46102 | C13: {=COUNTIF('어휘 - 표 1 스냅샷'!L2:L2503,B13)} -> 0 | D13: {=COUNTIF('외운 것 - 엑셀다운로드 파일(붙여넣기)'!C3:C562,B13)/100} -> 0
B14: 46103 | C14: {=COUNTIF('어휘 - 표 1 스냅샷'!L2:L2503,B14)} -> 0 | D14: {=COUNTIF('외운 것 - 엑셀다운로드 파일(붙여넣기)'!C3:C562,B14)/100} -> 0
B15: 46104 | C15: {=COUNTIF('어휘 - 표 1 스냅샷'!L2:L2503,B15)} -> 0 | D15: {=COUNTIF('외운 것 - 엑셀다운로드 파일(붙여넣기)'!C3:C562,B15)/100} -> 0
B16: 46105 | C16: {=COUNTIF('어휘 - 표 1 스냅샷'!L2:L2503,B16)} -> 0 | D16: {=COUNTIF('외운 것 - 엑셀다운로드 파일(붙여넣기)'!C3:C562,B16)/100} -> 0
B17: 46106 | C17: {=COUNTIF('어휘 - 표 1 스냅샷'!L2:L2503,B17)} -> 0 | D17: {=COUNTIF('외운 것 - 엑셀다운로드 파일(붙여넣기)'!C3:C562,B17)/100} -> 0
B18: 46107 | C18: {=COUNTIF('어휘 - 표 1 스냅샷'!L2:L2503,B18)} -> 0 | D18: {=COUNTIF('외운 것 - 엑셀다운로드 파일(붙여넣기)'!C3:C562,B18)/100} -> 0
B19: 46108 | C19: {=COUNTIF('어휘 - 표 1 스냅샷'!L2:L2503,B19)} -> 0 | D19: {=COUNTIF('외운 것 - 엑셀다운로드 파일(붙여넣기)'!C3:C562,B19)/100} -> 0
B20: 46109 | C20: {=COUNTIF('어휘 - 표 1 스냅샷'!L2:L2503,B20)} -> 0 | D20: {=COUNTIF('외운 것 - 엑셀다운로드 파일(붙여넣기)'!C3:C562,B20)/100} -> 0
B21: 46110 | C21: {=COUNTIF('어휘 - 표 1 스냅샷'!L2:L2503,B21)} -> 0 | D21: {=COUNTIF('외운 것 - 엑셀다운로드 파일(붙여넣기)'!C3:C562,B21)/100} -> 0
B22: 46111 | C22: {=COUNTIF('어휘 - 표 1 스냅샷'!L2:L2503,B22)} -> 0 | D22: {=COUNTIF('외운 것 - 엑셀다운로드 파일(붙여넣기)'!C3:C562,B22)/100} -> 0
B23: 46112 | C23: {=COUNTIF('어휘 - 표 1 스냅샷'!L2:L2503,B23)} -> 0 | D23: {=COUNTIF('외운 것 - 엑셀다운로드 파일(붙여넣기)'!C3:C562,B23)/100} -> 0
A24: 46113 | C24: =SUM(C25:C54) -> 0
B25: 46113 | C25: {=COUNTIF('어휘 - 표 1 스냅샷'!L2:L2503,B25)} -> 0 | D25: {=COUNTIF('외운 것 - 엑셀다운로드 파일(붙여넣기)'!C3:C562,B25)/100} -> 0
B26: 46114 | C26: {=COUNTIF('어휘 - 표 1 스냅샷'!L2:L2503,B26)} -> 0 | D26: {=COUNTIF('외운 것 - 엑셀다운로드 파일(붙여넣기)'!C3:C562,B26)/100} -> 0
B27: 46115 | C27: {=COUNTIF('어휘 - 표 1 스냅샷'!L2:L2503,B27)} -> 0 | D27: {=COUNTIF('외운 것 - 엑셀다운로드 파일(붙여넣기)'!C3:C562,B27)/100} -> 0
B28: 46116 | C28: {=COUNTIF('어휘 - 표 1 스냅샷'!L2:L2503,B28)} -> 0 | D28: {=COUNTIF('외운 것 - 엑셀다운로드 파일(붙여넣기)'!C3:C562,B28)/100} -> 0
B29: 46117 | C29: {=COUNTIF('어휘 - 표 1 스냅샷'!L2:L2503,B29)} -> 0 | D29: {=COUNTIF('외운 것 - 엑셀다운로드 파일(붙여넣기)'!C3:C562,B29)/100} -> 0
B30: 46118 | C30: {=COUNTIF('어휘 - 표 1 스냅샷'!L2:L2503,B30)} -> 0 | D30: {=COUNTIF('외운 것 - 엑셀다운로드 파일(붙여넣기)'!C3:C562,B30)/100} -> 0
B31: 46119 | C31: {=COUNTIF('어휘 - 표 1 스냅샷'!L2:L2503,B31)} -> 0 | D31: {=COUNTIF('외운 것 - 엑셀다운로드 파일(붙여넣기)'!C3:C562,B31)/100} -> 0
B32: 46120 | C32: {=COUNTIF('어휘 - 표 1 스냅샷'!L2:L2503,B32)} -> 0 | D32: {=COUNTIF('외운 것 - 엑셀다운로드 파일(붙여넣기)'!C3:C562,B32)/100} -> 0
B33: 46121 | C33: {=COUNTIF('어휘 - 표 1 스냅샷'!L2:L2503,B33)} -> 0 | D33: {=COUNTIF('외운 것 - 엑셀다운로드 파일(붙여넣기)'!C3:C562,B33)/100} -> 0
B34: 46122 | C34: {=COUNTIF('어휘 - 표 1 스냅샷'!L2:L2503,B34)} -> 0 | D34: {=COUNTIF('외운 것 - 엑셀다운로드 파일(붙여넣기)'!C3:C562,B34)/100} -> 0
B35: 46123 | C35: {=COUNTIF('어휘 - 표 1 스냅샷'!L2:L2503,B35)} -> 0 | D35: {=COUNTIF('외운 것 - 엑셀다운로드 파일(붙여넣기)'!C3:C562,B35)/100} -> 0
B36: 46124 | C36: {=COUNTIF('어휘 - 표 1 스냅샷'!L2:L2503,B36)} -> 0 | D36: {=COUNTIF('외운 것 - 엑셀다운로드 파일(붙여넣기)'!C3:C562,B36)/100} -> 0
B37: 46125 | C37: {=COUNTIF('어휘 - 표 1 스냅샷'!L2:L2503,B37)} -> 0 | D37: {=COUNTIF('외운 것 - 엑셀다운로드 파일(붙여넣기)'!C3:C562,B37)/100} -> 0
B38: 46126 | C38: {=COUNTIF('어휘 - 표 1 스냅샷'!L2:L2503,B38)} -> 0 | D38: {=COUNTIF('외운 것 - 엑셀다운로드 파일(붙여넣기)'!C3:C562,B38)/100} -> 0
B39: 46127 | C39: {=COUNTIF('어휘 - 표 1 스냅샷'!L2:L2503,B39)} -> 0 | D39: {=COUNTIF('외운 것 - 엑셀다운로드 파일(붙여넣기)'!C3:C562,B39)/100} -> 0
B40: 46128 | C40: {=COUNTIF('어휘 - 표 1 스냅샷'!L2:L2503,B40)} -> 0 | D40: {=COUNTIF('외운 것 - 엑셀다운로드 파일(붙여넣기)'!C3:C562,B40)/100} -> 0
B41: 46129 | C41: {=COUNTIF('어휘 - 표 1 스냅샷'!L2:L2503,B41)} -> 0 | D41: {=COUNTIF('외운 것 - 엑셀다운로드 파일(붙여넣기)'!C3:C562,B41)/100} -> 0
B42: 46130 | C42: {=COUNTIF('어휘 - 표 1 스냅샷'!L2:L2503,B42)} -> 0 | D42: {=COUNTIF('외운 것 - 엑셀다운로드 파일(붙여넣기)'!C3:C562,B42)/100} -> 0
B43: 46131 | C43: {=COUNTIF('어휘 - 표 1 스냅샷'!L2:L2503,B43)} -> 0 | D43: {=COUNTIF('외운 것 - 엑셀다운로드 파일(붙여넣기)'!C3:C562,B43)/100} -> 0
B44: 46132 | C44: {=COUNTIF('어휘 - 표 1 스냅샷'!L2:L2503,B44)} -> 0 | D44: {=COUNTIF('외운 것 - 엑셀다운로드 파일(붙여넣기)'!C3:C562,B44)/100} -> 0
B45: 46133 | C45: {=COUNTIF('어휘 - 표 1 스냅샷'!L2:L2503,B45)} -> 0 | D45: {=COUNTIF('외운 것 - 엑셀다운로드 파일(붙여넣기)'!C3:C562,B45)/100} -> 0
B46: 46134 | C46: {=COUNTIF('어휘 - 표 1 스냅샷'!L2:L2503,B46)} -> 0 | D46: {=COUNTIF('외운 것 - 엑셀다운로드 파일(붙여넣기)'!C3:C562,B46)/100} -> 0
B47: 46135 | C47: {=COUNTIF('어휘 - 표 1 스냅샷'!L2:L2503,B47)} -> 0 | D47: {=COUNTIF('외운 것 - 엑셀다운로드 파일(붙여넣기)'!C3:C562,B47)/100} -> 0
B48: 46136 | C48: {=COUNTIF('어휘 - 표 1 스냅샷'!L2:L2503,B48)} -> 0 | D48: {=COUNTIF('외운 것 - 엑셀다운로드 파일(붙여넣기)'!C3:C562,B48)/100} -> 0
B49: 46137 | C49: {=COUNTIF('어휘 - 표 1 스냅샷'!L2:L2503,B49)} -> 0 | D49: {=COUNTIF('외운 것 - 엑셀다운로드 파일(붙여넣기)'!C3:C562,B49)/100} -> 0
B50: 46138 | C50: {=COUNTIF('어휘 - 표 1 스냅샷'!L2:L2503,B50)} -> 0 | D50: {=COUNTIF('외운 것 - 엑셀다운로드 파일(붙여넣기)'!C3:C562,B50)/100} -> 0
B51: 46139 | C51: {=COUNTIF('어휘 - 표 1 스냅샷'!L2:L2503,B51)} -> 0 | D51: {=COUNTIF('외운 것 - 엑셀다운로드 파일(붙여넣기)'!C3:C562,B51)/100} -> 0
B52: 46140 | C52: {=COUNTIF('어휘 - 표 1 스냅샷'!L2:L2503,B52)} -> 0 | D52: {=COUNTIF('외운 것 - 엑셀다운로드 파일(붙여넣기)'!C3:C562,B52)/100} -> 0
B53: 46141 | C53: {=COUNTIF('어휘 - 표 1 스냅샷'!L2:L2503,B53)} -> 0 | D53: {=COUNTIF('외운 것 - 엑셀다운로드 파일(붙여넣기)'!C3:C562,B53)/100} -> 0
B54: 46142 | C54: {=COUNTIF('어휘 - 표 1 스냅샷'!L2:L2503,B54)} -> 0 | D54: {=COUNTIF('외운 것 - 엑셀다운로드 파일(붙여넣기)'!C3:C562,B54)/100} -> 0
A55: 46143 | C55: =SUM(C56:C86) -> 0
B56: 46143 | C56: {=COUNTIF('어휘 - 표 1 스냅샷'!L2:L2503,B56)} -> 0
B57: 46144 | C57: {=COUNTIF('어휘 - 표 1 스냅샷'!L2:L2503,B57)} -> 0
B58: 46145 | C58: {=COUNTIF('어휘 - 표 1 스냅샷'!L2:L2503,B58)} -> 0
B59: 46146 | C59: {=COUNTIF('어휘 - 표 1 스냅샷'!L2:L2503,B59)} -> 0
B60: 46147 | C60: {=COUNTIF('어휘 - 표 1 스냅샷'!L2:L2503,B60)} -> 0
B61: 46148 | C61: {=COUNTIF('어휘 - 표 1 스냅샷'!L2:L2503,B61)} -> 0
B62: 46149 | C62: {=COUNTIF('어휘 - 표 1 스냅샷'!L2:L2503,B62)} -> 0
B63: 46150 | C63: {=COUNTIF('어휘 - 표 1 스냅샷'!L2:L2503,B63)} -> 0
B64: 46151 | C64: {=COUNTIF('어휘 - 표 1 스냅샷'!L2:L2503,B64)} -> 0
B65: 46152 | C65: {=COUNTIF('어휘 - 표 1 스냅샷'!L2:L2503,B65)} -> 0
B66: 46153 | C66: {=COUNTIF('어휘 - 표 1 스냅샷'!L2:L2503,B66)} -> 0
B67: 46154 | C67: {=COUNTIF('어휘 - 표 1 스냅샷'!L2:L2503,B67)} -> 0
B68: 46155 | C68: {=COUNTIF('어휘 - 표 1 스냅샷'!L2:L2503,B68)} -> 0
B69: 46156 | C69: {=COUNTIF('어휘 - 표 1 스냅샷'!L2:L2503,B69)} -> 0
B70: 46157 | C70: {=COUNTIF('어휘 - 표 1 스냅샷'!L2:L2503,B70)} -> 0
B71: 46158 | C71: {=COUNTIF('어휘 - 표 1 스냅샷'!L2:L2503,B71)} -> 0
B72: 46159 | C72: {=COUNTIF('어휘 - 표 1 스냅샷'!L2:L2503,B72)} -> 0
B73: 46160 | C73: {=COUNTIF('어휘 - 표 1 스냅샷'!L2:L2503,B73)} -> 0
B74: 46161 | C74: {=COUNTIF('어휘 - 표 1 스냅샷'!L2:L2503,B74)} -> 0
B75: 46162 | C75: {=COUNTIF('어휘 - 표 1 스냅샷'!L2:L2503,B75)} -> 0
B76: 46163 | C76: {=COUNTIF('어휘 - 표 1 스냅샷'!L2:L2503,B76)} -> 0
B77: 46164 | C77: {=COUNTIF('어휘 - 표 1 스냅샷'!L2:L2503,B77)} -> 0
B78: 46165 | C78: {=COUNTIF('어휘 - 표 1 스냅샷'!L2:L2503,B78)} -> 0
B79: 46166 | C79: {=COUNTIF('어휘 - 표 1 스냅샷'!L2:L2503,B79)} -> 0
B80: 46167 | C80: {=COUNTIF('어휘 - 표 1 스냅샷'!L2:L2503,B80)} -> 0
B81: 46168 | C81: {=COUNTIF('어휘 - 표 1 스냅샷'!L2:L2503,B81)} -> 0
B82: 46169 | C82: {=COUNTIF('어휘 - 표 1 스냅샷'!L2:L2503,B82)} -> 0
B83: 46170 | C83: {=COUNTIF('어휘 - 표 1 스냅샷'!L2:L2503,B83)} -> 0
B84: 46171 | C84: {=COUNTIF('어휘 - 표 1 스냅샷'!L2:L2503,B84)} -> 0
B85: 46172 | C85: {=COUNTIF('어휘 - 표 1 스냅샷'!L2:L2503,B85)} -> 0
B86: 46173 | C86: {=COUNTIF('어휘 - 표 1 스냅샷'!L2:L2503,B86)} -> 0
A87: 46174 | C87: =SUM(C88:C117) -> 0
B88: 46174 | C88: {=COUNTIF('어휘 - 표 1 스냅샷'!L2:L2503,B88)} -> 0
B89: 46175 | C89: {=COUNTIF('어휘 - 표 1 스냅샷'!L2:L2503,B89)} -> 0
B90: 46176 | C90: {=COUNTIF('어휘 - 표 1 스냅샷'!L2:L2503,B90)} -> 0
B91: 46177 | C91: {=COUNTIF('어휘 - 표 1 스냅샷'!L2:L2503,B91)} -> 0
B92: 46178 | C92: {=COUNTIF('어휘 - 표 1 스냅샷'!L2:L2503,B92)} -> 0
B93: 46179 | C93: {=COUNTIF('어휘 - 표 1 스냅샷'!L2:L2503,B93)} -> 0
B94: 46180 | C94: {=COUNTIF('어휘 - 표 1 스냅샷'!L2:L2503,B94)} -> 0
B95: 46181 | C95: {=COUNTIF('어휘 - 표 1 스냅샷'!L2:L2503,B95)} -> 0
B96: 46182 | C96: {=COUNTIF('어휘 - 표 1 스냅샷'!L2:L2503,B96)} -> 0
B97: 46183 | C97: {=COUNTIF('어휘 - 표 1 스냅샷'!L2:L2503,B97)} -> 0
B98: 46184 | C98: {=COUNTIF('어휘 - 표 1 스냅샷'!L2:L2503,B98)} -> 0
B99: 46185 | C99: {=COUNTIF('어휘 - 표 1 스냅샷'!L2:L2503,B99)} -> 0
B100: 46186 | C100: {=COUNTIF('어휘 - 표 1 스냅샷'!L2:L2503,B100)} -> 0
...
